[
  {
    "name": "0",
    "position": {
      "x": 0,
      "y": 0
    }
  },
  {
    "name": "egg-manaphy",
    "position": {
      "x": 96,
      "y": 0
    }
  },
  {
    "name": "egg",
    "position": {
      "x": 192,
      "y": 0
    }
  },
  {
    "name": "substitute",
    "position": {
      "x": 288,
      "y": 0
    }
  },
  {
    "name": "1",
    "position": {
      "x": 384,
      "y": 0
    }
  },
  {
    "name": "2",
    "position": {
      "x": 480,
      "y": 0
    }
  },
  {
    "name": "3",
    "position": {
      "x": 576,
      "y": 0
    }
  },
  {
    "name": "4",
    "position": {
      "x": 672,
      "y": 0
    }
  },
  {
    "name": "5",
    "position": {
      "x": 768,
      "y": 0
    }
  },
  {
    "name": "6",
    "position": {
      "x": 864,
      "y": 0
    }
  },
  {
    "name": "7",
    "position": {
      "x": 960,
      "y": 0
    }
  },
  {
    "name": "8",
    "position": {
      "x": 1056,
      "y": 0
    }
  },
  {
    "name": "9",
    "position": {
      "x": 1152,
      "y": 0
    }
  },
  {
    "name": "10",
    "position": {
      "x": 1248,
      "y": 0
    }
  },
  {
    "name": "11",
    "position": {
      "x": 1344,
      "y": 0
    }
  },
  {
    "name": "12",
    "position": {
      "x": 1440,
      "y": 0
    }
  },
  {
    "name": "13",
    "position": {
      "x": 1536,
      "y": 0
    }
  },
  {
    "name": "14",
    "position": {
      "x": 1632,
      "y": 0
    }
  },
  {
    "name": "15",
    "position": {
      "x": 1728,
      "y": 0
    }
  },
  {
    "name": "16",
    "position": {
      "x": 1824,
      "y": 0
    }
  },
  {
    "name": "17",
    "position": {
      "x": 1920,
      "y": 0
    }
  },
  {
    "name": "18",
    "position": {
      "x": 2016,
      "y": 0
    }
  },
  {
    "name": "19",
    "position": {
      "x": 2112,
      "y": 0
    }
  },
  {
    "name": "20",
    "position": {
      "x": 2208,
      "y": 0
    }
  },
  {
    "name": "21",
    "position": {
      "x": 2304,
      "y": 0
    }
  },
  {
    "name": "22",
    "position": {
      "x": 2400,
      "y": 0
    }
  },
  {
    "name": "23",
    "position": {
      "x": 2496,
      "y": 0
    }
  },
  {
    "name": "24",
    "position": {
      "x": 2592,
      "y": 0
    }
  },
  {
    "name": "25",
    "position": {
      "x": 2688,
      "y": 0
    }
  },
  {
    "name": "26",
    "position": {
      "x": 2784,
      "y": 0
    }
  },
  {
    "name": "27",
    "position": {
      "x": 2880,
      "y": 0
    }
  },
  {
    "name": "28",
    "position": {
      "x": 2976,
      "y": 0
    }
  },
  {
    "name": "29",
    "position": {
      "x": 3072,
      "y": 0
    }
  },
  {
    "name": "30",
    "position": {
      "x": 0,
      "y": 96
    }
  },
  {
    "name": "31",
    "position": {
      "x": 96,
      "y": 96
    }
  },
  {
    "name": "32",
    "position": {
      "x": 192,
      "y": 96
    }
  },
  {
    "name": "33",
    "position": {
      "x": 288,
      "y": 96
    }
  },
  {
    "name": "34",
    "position": {
      "x": 384,
      "y": 96
    }
  },
  {
    "name": "35",
    "position": {
      "x": 480,
      "y": 96
    }
  },
  {
    "name": "36",
    "position": {
      "x": 576,
      "y": 96
    }
  },
  {
    "name": "37",
    "position": {
      "x": 672,
      "y": 96
    }
  },
  {
    "name": "38",
    "position": {
      "x": 768,
      "y": 96
    }
  },
  {
    "name": "39",
    "position": {
      "x": 864,
      "y": 96
    }
  },
  {
    "name": "40",
    "position": {
      "x": 960,
      "y": 96
    }
  },
  {
    "name": "41",
    "position": {
      "x": 1056,
      "y": 96
    }
  },
  {
    "name": "42",
    "position": {
      "x": 1152,
      "y": 96
    }
  },
  {
    "name": "43",
    "position": {
      "x": 1248,
      "y": 96
    }
  },
  {
    "name": "44",
    "position": {
      "x": 1344,
      "y": 96
    }
  },
  {
    "name": "45",
    "position": {
      "x": 1440,
      "y": 96
    }
  },
  {
    "name": "46",
    "position": {
      "x": 1536,
      "y": 96
    }
  },
  {
    "name": "47",
    "position": {
      "x": 1632,
      "y": 96
    }
  },
  {
    "name": "48",
    "position": {
      "x": 1728,
      "y": 96
    }
  },
  {
    "name": "49",
    "position": {
      "x": 1824,
      "y": 96
    }
  },
  {
    "name": "50",
    "position": {
      "x": 1920,
      "y": 96
    }
  },
  {
    "name": "51",
    "position": {
      "x": 2016,
      "y": 96
    }
  },
  {
    "name": "52",
    "position": {
      "x": 2112,
      "y": 96
    }
  },
  {
    "name": "53",
    "position": {
      "x": 2208,
      "y": 96
    }
  },
  {
    "name": "54",
    "position": {
      "x": 2304,
      "y": 96
    }
  },
  {
    "name": "55",
    "position": {
      "x": 2400,
      "y": 96
    }
  },
  {
    "name": "56",
    "position": {
      "x": 2496,
      "y": 96
    }
  },
  {
    "name": "57",
    "position": {
      "x": 2592,
      "y": 96
    }
  },
  {
    "name": "58",
    "position": {
      "x": 2688,
      "y": 96
    }
  },
  {
    "name": "59",
    "position": {
      "x": 2784,
      "y": 96
    }
  },
  {
    "name": "60",
    "position": {
      "x": 2880,
      "y": 96
    }
  },
  {
    "name": "61",
    "position": {
      "x": 2976,
      "y": 96
    }
  },
  {
    "name": "62",
    "position": {
      "x": 3072,
      "y": 96
    }
  },
  {
    "name": "63",
    "position": {
      "x": 0,
      "y": 192
    }
  },
  {
    "name": "64",
    "position": {
      "x": 96,
      "y": 192
    }
  },
  {
    "name": "65",
    "position": {
      "x": 192,
      "y": 192
    }
  },
  {
    "name": "66",
    "position": {
      "x": 288,
      "y": 192
    }
  },
  {
    "name": "67",
    "position": {
      "x": 384,
      "y": 192
    }
  },
  {
    "name": "68",
    "position": {
      "x": 480,
      "y": 192
    }
  },
  {
    "name": "69",
    "position": {
      "x": 576,
      "y": 192
    }
  },
  {
    "name": "70",
    "position": {
      "x": 672,
      "y": 192
    }
  },
  {
    "name": "71",
    "position": {
      "x": 768,
      "y": 192
    }
  },
  {
    "name": "72",
    "position": {
      "x": 864,
      "y": 192
    }
  },
  {
    "name": "73",
    "position": {
      "x": 960,
      "y": 192
    }
  },
  {
    "name": "74",
    "position": {
      "x": 1056,
      "y": 192
    }
  },
  {
    "name": "75",
    "position": {
      "x": 1152,
      "y": 192
    }
  },
  {
    "name": "76",
    "position": {
      "x": 1248,
      "y": 192
    }
  },
  {
    "name": "77",
    "position": {
      "x": 1344,
      "y": 192
    }
  },
  {
    "name": "78",
    "position": {
      "x": 1440,
      "y": 192
    }
  },
  {
    "name": "79",
    "position": {
      "x": 1536,
      "y": 192
    }
  },
  {
    "name": "80",
    "position": {
      "x": 1632,
      "y": 192
    }
  },
  {
    "name": "81",
    "position": {
      "x": 1728,
      "y": 192
    }
  },
  {
    "name": "82",
    "position": {
      "x": 1824,
      "y": 192
    }
  },
  {
    "name": "83",
    "position": {
      "x": 1920,
      "y": 192
    }
  },
  {
    "name": "84",
    "position": {
      "x": 2016,
      "y": 192
    }
  },
  {
    "name": "85",
    "position": {
      "x": 2112,
      "y": 192
    }
  },
  {
    "name": "86",
    "position": {
      "x": 2208,
      "y": 192
    }
  },
  {
    "name": "87",
    "position": {
      "x": 2304,
      "y": 192
    }
  },
  {
    "name": "88",
    "position": {
      "x": 2400,
      "y": 192
    }
  },
  {
    "name": "89",
    "position": {
      "x": 2496,
      "y": 192
    }
  },
  {
    "name": "90",
    "position": {
      "x": 2592,
      "y": 192
    }
  },
  {
    "name": "91",
    "position": {
      "x": 2688,
      "y": 192
    }
  },
  {
    "name": "92",
    "position": {
      "x": 2784,
      "y": 192
    }
  },
  {
    "name": "93",
    "position": {
      "x": 2880,
      "y": 192
    }
  },
  {
    "name": "94",
    "position": {
      "x": 2976,
      "y": 192
    }
  },
  {
    "name": "95",
    "position": {
      "x": 3072,
      "y": 192
    }
  },
  {
    "name": "96",
    "position": {
      "x": 0,
      "y": 288
    }
  },
  {
    "name": "97",
    "position": {
      "x": 96,
      "y": 288
    }
  },
  {
    "name": "98",
    "position": {
      "x": 192,
      "y": 288
    }
  },
  {
    "name": "99",
    "position": {
      "x": 288,
      "y": 288
    }
  },
  {
    "name": "100",
    "position": {
      "x": 384,
      "y": 288
    }
  },
  {
    "name": "101",
    "position": {
      "x": 480,
      "y": 288
    }
  },
  {
    "name": "102",
    "position": {
      "x": 576,
      "y": 288
    }
  },
  {
    "name": "103",
    "position": {
      "x": 672,
      "y": 288
    }
  },
  {
    "name": "104",
    "position": {
      "x": 768,
      "y": 288
    }
  },
  {
    "name": "105",
    "position": {
      "x": 864,
      "y": 288
    }
  },
  {
    "name": "106",
    "position": {
      "x": 960,
      "y": 288
    }
  },
  {
    "name": "107",
    "position": {
      "x": 1056,
      "y": 288
    }
  },
  {
    "name": "108",
    "position": {
      "x": 1152,
      "y": 288
    }
  },
  {
    "name": "109",
    "position": {
      "x": 1248,
      "y": 288
    }
  },
  {
    "name": "110",
    "position": {
      "x": 1344,
      "y": 288
    }
  },
  {
    "name": "111",
    "position": {
      "x": 1440,
      "y": 288
    }
  },
  {
    "name": "112",
    "position": {
      "x": 1536,
      "y": 288
    }
  },
  {
    "name": "113",
    "position": {
      "x": 1632,
      "y": 288
    }
  },
  {
    "name": "114",
    "position": {
      "x": 1728,
      "y": 288
    }
  },
  {
    "name": "115",
    "position": {
      "x": 1824,
      "y": 288
    }
  },
  {
    "name": "116",
    "position": {
      "x": 1920,
      "y": 288
    }
  },
  {
    "name": "117",
    "position": {
      "x": 2016,
      "y": 288
    }
  },
  {
    "name": "118",
    "position": {
      "x": 2112,
      "y": 288
    }
  },
  {
    "name": "119",
    "position": {
      "x": 2208,
      "y": 288
    }
  },
  {
    "name": "120",
    "position": {
      "x": 2304,
      "y": 288
    }
  },
  {
    "name": "121",
    "position": {
      "x": 2400,
      "y": 288
    }
  },
  {
    "name": "122",
    "position": {
      "x": 2496,
      "y": 288
    }
  },
  {
    "name": "123",
    "position": {
      "x": 2592,
      "y": 288
    }
  },
  {
    "name": "124",
    "position": {
      "x": 2688,
      "y": 288
    }
  },
  {
    "name": "125",
    "position": {
      "x": 2784,
      "y": 288
    }
  },
  {
    "name": "126",
    "position": {
      "x": 2880,
      "y": 288
    }
  },
  {
    "name": "127",
    "position": {
      "x": 2976,
      "y": 288
    }
  },
  {
    "name": "128",
    "position": {
      "x": 3072,
      "y": 288
    }
  },
  {
    "name": "129",
    "position": {
      "x": 0,
      "y": 384
    }
  },
  {
    "name": "130",
    "position": {
      "x": 96,
      "y": 384
    }
  },
  {
    "name": "131",
    "position": {
      "x": 192,
      "y": 384
    }
  },
  {
    "name": "132",
    "position": {
      "x": 288,
      "y": 384
    }
  },
  {
    "name": "133",
    "position": {
      "x": 384,
      "y": 384
    }
  },
  {
    "name": "134",
    "position": {
      "x": 480,
      "y": 384
    }
  },
  {
    "name": "135",
    "position": {
      "x": 576,
      "y": 384
    }
  },
  {
    "name": "136",
    "position": {
      "x": 672,
      "y": 384
    }
  },
  {
    "name": "137",
    "position": {
      "x": 768,
      "y": 384
    }
  },
  {
    "name": "138",
    "position": {
      "x": 864,
      "y": 384
    }
  },
  {
    "name": "139",
    "position": {
      "x": 960,
      "y": 384
    }
  },
  {
    "name": "140",
    "position": {
      "x": 1056,
      "y": 384
    }
  },
  {
    "name": "141",
    "position": {
      "x": 1152,
      "y": 384
    }
  },
  {
    "name": "142",
    "position": {
      "x": 1248,
      "y": 384
    }
  },
  {
    "name": "143",
    "position": {
      "x": 1344,
      "y": 384
    }
  },
  {
    "name": "144",
    "position": {
      "x": 1440,
      "y": 384
    }
  },
  {
    "name": "145",
    "position": {
      "x": 1536,
      "y": 384
    }
  },
  {
    "name": "146",
    "position": {
      "x": 1632,
      "y": 384
    }
  },
  {
    "name": "147",
    "position": {
      "x": 1728,
      "y": 384
    }
  },
  {
    "name": "148",
    "position": {
      "x": 1824,
      "y": 384
    }
  },
  {
    "name": "149",
    "position": {
      "x": 1920,
      "y": 384
    }
  },
  {
    "name": "150",
    "position": {
      "x": 2016,
      "y": 384
    }
  },
  {
    "name": "151",
    "position": {
      "x": 2112,
      "y": 384
    }
  },
  {
    "name": "152",
    "position": {
      "x": 2208,
      "y": 384
    }
  },
  {
    "name": "153",
    "position": {
      "x": 2304,
      "y": 384
    }
  },
  {
    "name": "154",
    "position": {
      "x": 2400,
      "y": 384
    }
  },
  {
    "name": "155",
    "position": {
      "x": 2496,
      "y": 384
    }
  },
  {
    "name": "156",
    "position": {
      "x": 2592,
      "y": 384
    }
  },
  {
    "name": "157",
    "position": {
      "x": 2688,
      "y": 384
    }
  },
  {
    "name": "158",
    "position": {
      "x": 2784,
      "y": 384
    }
  },
  {
    "name": "159",
    "position": {
      "x": 2880,
      "y": 384
    }
  },
  {
    "name": "160",
    "position": {
      "x": 2976,
      "y": 384
    }
  },
  {
    "name": "161",
    "position": {
      "x": 3072,
      "y": 384
    }
  },
  {
    "name": "162",
    "position": {
      "x": 0,
      "y": 480
    }
  },
  {
    "name": "163",
    "position": {
      "x": 96,
      "y": 480
    }
  },
  {
    "name": "164",
    "position": {
      "x": 192,
      "y": 480
    }
  },
  {
    "name": "165",
    "position": {
      "x": 288,
      "y": 480
    }
  },
  {
    "name": "166",
    "position": {
      "x": 384,
      "y": 480
    }
  },
  {
    "name": "167",
    "position": {
      "x": 480,
      "y": 480
    }
  },
  {
    "name": "168",
    "position": {
      "x": 576,
      "y": 480
    }
  },
  {
    "name": "169",
    "position": {
      "x": 672,
      "y": 480
    }
  },
  {
    "name": "170",
    "position": {
      "x": 768,
      "y": 480
    }
  },
  {
    "name": "171",
    "position": {
      "x": 864,
      "y": 480
    }
  },
  {
    "name": "172",
    "position": {
      "x": 960,
      "y": 480
    }
  },
  {
    "name": "173",
    "position": {
      "x": 1056,
      "y": 480
    }
  },
  {
    "name": "174",
    "position": {
      "x": 1152,
      "y": 480
    }
  },
  {
    "name": "175",
    "position": {
      "x": 1248,
      "y": 480
    }
  },
  {
    "name": "176",
    "position": {
      "x": 1344,
      "y": 480
    }
  },
  {
    "name": "177",
    "position": {
      "x": 1440,
      "y": 480
    }
  },
  {
    "name": "178",
    "position": {
      "x": 1536,
      "y": 480
    }
  },
  {
    "name": "179",
    "position": {
      "x": 1632,
      "y": 480
    }
  },
  {
    "name": "180",
    "position": {
      "x": 1728,
      "y": 480
    }
  },
  {
    "name": "181",
    "position": {
      "x": 1824,
      "y": 480
    }
  },
  {
    "name": "182",
    "position": {
      "x": 1920,
      "y": 480
    }
  },
  {
    "name": "183",
    "position": {
      "x": 2016,
      "y": 480
    }
  },
  {
    "name": "184",
    "position": {
      "x": 2112,
      "y": 480
    }
  },
  {
    "name": "185",
    "position": {
      "x": 2208,
      "y": 480
    }
  },
  {
    "name": "186",
    "position": {
      "x": 2304,
      "y": 480
    }
  },
  {
    "name": "187",
    "position": {
      "x": 2400,
      "y": 480
    }
  },
  {
    "name": "188",
    "position": {
      "x": 2496,
      "y": 480
    }
  },
  {
    "name": "189",
    "position": {
      "x": 2592,
      "y": 480
    }
  },
  {
    "name": "190",
    "position": {
      "x": 2688,
      "y": 480
    }
  },
  {
    "name": "191",
    "position": {
      "x": 2784,
      "y": 480
    }
  },
  {
    "name": "192",
    "position": {
      "x": 2880,
      "y": 480
    }
  },
  {
    "name": "193",
    "position": {
      "x": 2976,
      "y": 480
    }
  },
  {
    "name": "194",
    "position": {
      "x": 3072,
      "y": 480
    }
  },
  {
    "name": "195",
    "position": {
      "x": 0,
      "y": 576
    }
  },
  {
    "name": "196",
    "position": {
      "x": 96,
      "y": 576
    }
  },
  {
    "name": "197",
    "position": {
      "x": 192,
      "y": 576
    }
  },
  {
    "name": "198",
    "position": {
      "x": 288,
      "y": 576
    }
  },
  {
    "name": "199",
    "position": {
      "x": 384,
      "y": 576
    }
  },
  {
    "name": "200",
    "position": {
      "x": 480,
      "y": 576
    }
  },
  {
    "name": "201-a",
    "position": {
      "x": 576,
      "y": 576
    }
  },
  {
    "name": "201-b",
    "position": {
      "x": 672,
      "y": 576
    }
  },
  {
    "name": "201-c",
    "position": {
      "x": 768,
      "y": 576
    }
  },
  {
    "name": "201-d",
    "position": {
      "x": 864,
      "y": 576
    }
  },
  {
    "name": "201-e",
    "position": {
      "x": 960,
      "y": 576
    }
  },
  {
    "name": "201-exclamation",
    "position": {
      "x": 1056,
      "y": 576
    }
  },
  {
    "name": "201-f",
    "position": {
      "x": 1152,
      "y": 576
    }
  },
  {
    "name": "201-g",
    "position": {
      "x": 1248,
      "y": 576
    }
  },
  {
    "name": "201-h",
    "position": {
      "x": 1344,
      "y": 576
    }
  },
  {
    "name": "201-i",
    "position": {
      "x": 1440,
      "y": 576
    }
  },
  {
    "name": "201-j",
    "position": {
      "x": 1536,
      "y": 576
    }
  },
  {
    "name": "201-k",
    "position": {
      "x": 1632,
      "y": 576
    }
  },
  {
    "name": "201-l",
    "position": {
      "x": 1728,
      "y": 576
    }
  },
  {
    "name": "201-m",
    "position": {
      "x": 1824,
      "y": 576
    }
  },
  {
    "name": "201-n",
    "position": {
      "x": 1920,
      "y": 576
    }
  },
  {
    "name": "201-o",
    "position": {
      "x": 2016,
      "y": 576
    }
  },
  {
    "name": "201-p",
    "position": {
      "x": 2112,
      "y": 576
    }
  },
  {
    "name": "201-q",
    "position": {
      "x": 2208,
      "y": 576
    }
  },
  {
    "name": "201-question",
    "position": {
      "x": 2304,
      "y": 576
    }
  },
  {
    "name": "201-r",
    "position": {
      "x": 2400,
      "y": 576
    }
  },
  {
    "name": "201-s",
    "position": {
      "x": 2496,
      "y": 576
    }
  },
  {
    "name": "201-t",
    "position": {
      "x": 2592,
      "y": 576
    }
  },
  {
    "name": "201-u",
    "position": {
      "x": 2688,
      "y": 576
    }
  },
  {
    "name": "201-v",
    "position": {
      "x": 2784,
      "y": 576
    }
  },
  {
    "name": "201-w",
    "position": {
      "x": 2880,
      "y": 576
    }
  },
  {
    "name": "201-x",
    "position": {
      "x": 2976,
      "y": 576
    }
  },
  {
    "name": "201-y",
    "position": {
      "x": 3072,
      "y": 576
    }
  },
  {
    "name": "201-z",
    "position": {
      "x": 0,
      "y": 672
    }
  },
  {
    "name": "201",
    "position": {
      "x": 96,
      "y": 672
    }
  },
  {
    "name": "202",
    "position": {
      "x": 192,
      "y": 672
    }
  },
  {
    "name": "203",
    "position": {
      "x": 288,
      "y": 672
    }
  },
  {
    "name": "204",
    "position": {
      "x": 384,
      "y": 672
    }
  },
  {
    "name": "205",
    "position": {
      "x": 480,
      "y": 672
    }
  },
  {
    "name": "206",
    "position": {
      "x": 576,
      "y": 672
    }
  },
  {
    "name": "207",
    "position": {
      "x": 672,
      "y": 672
    }
  },
  {
    "name": "208",
    "position": {
      "x": 768,
      "y": 672
    }
  },
  {
    "name": "209",
    "position": {
      "x": 864,
      "y": 672
    }
  },
  {
    "name": "210",
    "position": {
      "x": 960,
      "y": 672
    }
  },
  {
    "name": "211",
    "position": {
      "x": 1056,
      "y": 672
    }
  },
  {
    "name": "212",
    "position": {
      "x": 1152,
      "y": 672
    }
  },
  {
    "name": "213",
    "position": {
      "x": 1248,
      "y": 672
    }
  },
  {
    "name": "214",
    "position": {
      "x": 1344,
      "y": 672
    }
  },
  {
    "name": "215",
    "position": {
      "x": 1440,
      "y": 672
    }
  },
  {
    "name": "216",
    "position": {
      "x": 1536,
      "y": 672
    }
  },
  {
    "name": "217",
    "position": {
      "x": 1632,
      "y": 672
    }
  },
  {
    "name": "218",
    "position": {
      "x": 1728,
      "y": 672
    }
  },
  {
    "name": "219",
    "position": {
      "x": 1824,
      "y": 672
    }
  },
  {
    "name": "220",
    "position": {
      "x": 1920,
      "y": 672
    }
  },
  {
    "name": "221",
    "position": {
      "x": 2016,
      "y": 672
    }
  },
  {
    "name": "222",
    "position": {
      "x": 2112,
      "y": 672
    }
  },
  {
    "name": "223",
    "position": {
      "x": 2208,
      "y": 672
    }
  },
  {
    "name": "224",
    "position": {
      "x": 2304,
      "y": 672
    }
  },
  {
    "name": "225",
    "position": {
      "x": 2400,
      "y": 672
    }
  },
  {
    "name": "226",
    "position": {
      "x": 2496,
      "y": 672
    }
  },
  {
    "name": "227",
    "position": {
      "x": 2592,
      "y": 672
    }
  },
  {
    "name": "228",
    "position": {
      "x": 2688,
      "y": 672
    }
  },
  {
    "name": "229",
    "position": {
      "x": 2784,
      "y": 672
    }
  },
  {
    "name": "230",
    "position": {
      "x": 2880,
      "y": 672
    }
  },
  {
    "name": "231",
    "position": {
      "x": 2976,
      "y": 672
    }
  },
  {
    "name": "232",
    "position": {
      "x": 3072,
      "y": 672
    }
  },
  {
    "name": "233",
    "position": {
      "x": 0,
      "y": 768
    }
  },
  {
    "name": "234",
    "position": {
      "x": 96,
      "y": 768
    }
  },
  {
    "name": "235",
    "position": {
      "x": 192,
      "y": 768
    }
  },
  {
    "name": "236",
    "position": {
      "x": 288,
      "y": 768
    }
  },
  {
    "name": "237",
    "position": {
      "x": 384,
      "y": 768
    }
  },
  {
    "name": "238",
    "position": {
      "x": 480,
      "y": 768
    }
  },
  {
    "name": "239",
    "position": {
      "x": 576,
      "y": 768
    }
  },
  {
    "name": "240",
    "position": {
      "x": 672,
      "y": 768
    }
  },
  {
    "name": "241",
    "position": {
      "x": 768,
      "y": 768
    }
  },
  {
    "name": "242",
    "position": {
      "x": 864,
      "y": 768
    }
  },
  {
    "name": "243",
    "position": {
      "x": 960,
      "y": 768
    }
  },
  {
    "name": "244",
    "position": {
      "x": 1056,
      "y": 768
    }
  },
  {
    "name": "245",
    "position": {
      "x": 1152,
      "y": 768
    }
  },
  {
    "name": "246",
    "position": {
      "x": 1248,
      "y": 768
    }
  },
  {
    "name": "247",
    "position": {
      "x": 1344,
      "y": 768
    }
  },
  {
    "name": "248",
    "position": {
      "x": 1440,
      "y": 768
    }
  },
  {
    "name": "249",
    "position": {
      "x": 1536,
      "y": 768
    }
  },
  {
    "name": "250",
    "position": {
      "x": 1632,
      "y": 768
    }
  },
  {
    "name": "251",
    "position": {
      "x": 1728,
      "y": 768
    }
  },
  {
    "name": "252",
    "position": {
      "x": 1824,
      "y": 768
    }
  },
  {
    "name": "253",
    "position": {
      "x": 1920,
      "y": 768
    }
  },
  {
    "name": "254",
    "position": {
      "x": 2016,
      "y": 768
    }
  },
  {
    "name": "255",
    "position": {
      "x": 2112,
      "y": 768
    }
  },
  {
    "name": "256",
    "position": {
      "x": 2208,
      "y": 768
    }
  },
  {
    "name": "257",
    "position": {
      "x": 2304,
      "y": 768
    }
  },
  {
    "name": "258",
    "position": {
      "x": 2400,
      "y": 768
    }
  },
  {
    "name": "259",
    "position": {
      "x": 2496,
      "y": 768
    }
  },
  {
    "name": "260",
    "position": {
      "x": 2592,
      "y": 768
    }
  },
  {
    "name": "261",
    "position": {
      "x": 2688,
      "y": 768
    }
  },
  {
    "name": "262",
    "position": {
      "x": 2784,
      "y": 768
    }
  },
  {
    "name": "263",
    "position": {
      "x": 2880,
      "y": 768
    }
  },
  {
    "name": "264",
    "position": {
      "x": 2976,
      "y": 768
    }
  },
  {
    "name": "265",
    "position": {
      "x": 3072,
      "y": 768
    }
  },
  {
    "name": "266",
    "position": {
      "x": 0,
      "y": 864
    }
  },
  {
    "name": "267",
    "position": {
      "x": 96,
      "y": 864
    }
  },
  {
    "name": "268",
    "position": {
      "x": 192,
      "y": 864
    }
  },
  {
    "name": "269",
    "position": {
      "x": 288,
      "y": 864
    }
  },
  {
    "name": "270",
    "position": {
      "x": 384,
      "y": 864
    }
  },
  {
    "name": "271",
    "position": {
      "x": 480,
      "y": 864
    }
  },
  {
    "name": "272",
    "position": {
      "x": 576,
      "y": 864
    }
  },
  {
    "name": "273",
    "position": {
      "x": 672,
      "y": 864
    }
  },
  {
    "name": "274",
    "position": {
      "x": 768,
      "y": 864
    }
  },
  {
    "name": "275",
    "position": {
      "x": 864,
      "y": 864
    }
  },
  {
    "name": "276",
    "position": {
      "x": 960,
      "y": 864
    }
  },
  {
    "name": "277",
    "position": {
      "x": 1056,
      "y": 864
    }
  },
  {
    "name": "278",
    "position": {
      "x": 1152,
      "y": 864
    }
  },
  {
    "name": "279",
    "position": {
      "x": 1248,
      "y": 864
    }
  },
  {
    "name": "280",
    "position": {
      "x": 1344,
      "y": 864
    }
  },
  {
    "name": "281",
    "position": {
      "x": 1440,
      "y": 864
    }
  },
  {
    "name": "282",
    "position": {
      "x": 1536,
      "y": 864
    }
  },
  {
    "name": "283",
    "position": {
      "x": 1632,
      "y": 864
    }
  },
  {
    "name": "284",
    "position": {
      "x": 1728,
      "y": 864
    }
  },
  {
    "name": "285",
    "position": {
      "x": 1824,
      "y": 864
    }
  },
  {
    "name": "286",
    "position": {
      "x": 1920,
      "y": 864
    }
  },
  {
    "name": "287",
    "position": {
      "x": 2016,
      "y": 864
    }
  },
  {
    "name": "288",
    "position": {
      "x": 2112,
      "y": 864
    }
  },
  {
    "name": "289",
    "position": {
      "x": 2208,
      "y": 864
    }
  },
  {
    "name": "290",
    "position": {
      "x": 2304,
      "y": 864
    }
  },
  {
    "name": "291",
    "position": {
      "x": 2400,
      "y": 864
    }
  },
  {
    "name": "292",
    "position": {
      "x": 2496,
      "y": 864
    }
  },
  {
    "name": "293",
    "position": {
      "x": 2592,
      "y": 864
    }
  },
  {
    "name": "294",
    "position": {
      "x": 2688,
      "y": 864
    }
  },
  {
    "name": "295",
    "position": {
      "x": 2784,
      "y": 864
    }
  },
  {
    "name": "296",
    "position": {
      "x": 2880,
      "y": 864
    }
  },
  {
    "name": "297",
    "position": {
      "x": 2976,
      "y": 864
    }
  },
  {
    "name": "298",
    "position": {
      "x": 3072,
      "y": 864
    }
  },
  {
    "name": "299",
    "position": {
      "x": 0,
      "y": 960
    }
  },
  {
    "name": "300",
    "position": {
      "x": 96,
      "y": 960
    }
  },
  {
    "name": "301",
    "position": {
      "x": 192,
      "y": 960
    }
  },
  {
    "name": "302",
    "position": {
      "x": 288,
      "y": 960
    }
  },
  {
    "name": "303",
    "position": {
      "x": 384,
      "y": 960
    }
  },
  {
    "name": "304",
    "position": {
      "x": 480,
      "y": 960
    }
  },
  {
    "name": "305",
    "position": {
      "x": 576,
      "y": 960
    }
  },
  {
    "name": "306",
    "position": {
      "x": 672,
      "y": 960
    }
  },
  {
    "name": "307",
    "position": {
      "x": 768,
      "y": 960
    }
  },
  {
    "name": "308",
    "position": {
      "x": 864,
      "y": 960
    }
  },
  {
    "name": "309",
    "position": {
      "x": 960,
      "y": 960
    }
  },
  {
    "name": "310",
    "position": {
      "x": 1056,
      "y": 960
    }
  },
  {
    "name": "311",
    "position": {
      "x": 1152,
      "y": 960
    }
  },
  {
    "name": "312",
    "position": {
      "x": 1248,
      "y": 960
    }
  },
  {
    "name": "313",
    "position": {
      "x": 1344,
      "y": 960
    }
  },
  {
    "name": "314",
    "position": {
      "x": 1440,
      "y": 960
    }
  },
  {
    "name": "315",
    "position": {
      "x": 1536,
      "y": 960
    }
  },
  {
    "name": "316",
    "position": {
      "x": 1632,
      "y": 960
    }
  },
  {
    "name": "317",
    "position": {
      "x": 1728,
      "y": 960
    }
  },
  {
    "name": "318",
    "position": {
      "x": 1824,
      "y": 960
    }
  },
  {
    "name": "319",
    "position": {
      "x": 1920,
      "y": 960
    }
  },
  {
    "name": "320",
    "position": {
      "x": 2016,
      "y": 960
    }
  },
  {
    "name": "321",
    "position": {
      "x": 2112,
      "y": 960
    }
  },
  {
    "name": "322",
    "position": {
      "x": 2208,
      "y": 960
    }
  },
  {
    "name": "323",
    "position": {
      "x": 2304,
      "y": 960
    }
  },
  {
    "name": "324",
    "position": {
      "x": 2400,
      "y": 960
    }
  },
  {
    "name": "325",
    "position": {
      "x": 2496,
      "y": 960
    }
  },
  {
    "name": "326",
    "position": {
      "x": 2592,
      "y": 960
    }
  },
  {
    "name": "327",
    "position": {
      "x": 2688,
      "y": 960
    }
  },
  {
    "name": "328",
    "position": {
      "x": 2784,
      "y": 960
    }
  },
  {
    "name": "329",
    "position": {
      "x": 2880,
      "y": 960
    }
  },
  {
    "name": "330",
    "position": {
      "x": 2976,
      "y": 960
    }
  },
  {
    "name": "331",
    "position": {
      "x": 3072,
      "y": 960
    }
  },
  {
    "name": "332",
    "position": {
      "x": 0,
      "y": 1056
    }
  },
  {
    "name": "333",
    "position": {
      "x": 96,
      "y": 1056
    }
  },
  {
    "name": "334",
    "position": {
      "x": 192,
      "y": 1056
    }
  },
  {
    "name": "335",
    "position": {
      "x": 288,
      "y": 1056
    }
  },
  {
    "name": "336",
    "position": {
      "x": 384,
      "y": 1056
    }
  },
  {
    "name": "337",
    "position": {
      "x": 480,
      "y": 1056
    }
  },
  {
    "name": "338",
    "position": {
      "x": 576,
      "y": 1056
    }
  },
  {
    "name": "339",
    "position": {
      "x": 672,
      "y": 1056
    }
  },
  {
    "name": "340",
    "position": {
      "x": 768,
      "y": 1056
    }
  },
  {
    "name": "341",
    "position": {
      "x": 864,
      "y": 1056
    }
  },
  {
    "name": "342",
    "position": {
      "x": 960,
      "y": 1056
    }
  },
  {
    "name": "343",
    "position": {
      "x": 1056,
      "y": 1056
    }
  },
  {
    "name": "344",
    "position": {
      "x": 1152,
      "y": 1056
    }
  },
  {
    "name": "345",
    "position": {
      "x": 1248,
      "y": 1056
    }
  },
  {
    "name": "346",
    "position": {
      "x": 1344,
      "y": 1056
    }
  },
  {
    "name": "347",
    "position": {
      "x": 1440,
      "y": 1056
    }
  },
  {
    "name": "348",
    "position": {
      "x": 1536,
      "y": 1056
    }
  },
  {
    "name": "349",
    "position": {
      "x": 1632,
      "y": 1056
    }
  },
  {
    "name": "350",
    "position": {
      "x": 1728,
      "y": 1056
    }
  },
  {
    "name": "351-rainy",
    "position": {
      "x": 1824,
      "y": 1056
    }
  },
  {
    "name": "351-snowy",
    "position": {
      "x": 1920,
      "y": 1056
    }
  },
  {
    "name": "351-sunny",
    "position": {
      "x": 2016,
      "y": 1056
    }
  },
  {
    "name": "351",
    "position": {
      "x": 2112,
      "y": 1056
    }
  },
  {
    "name": "352",
    "position": {
      "x": 2208,
      "y": 1056
    }
  },
  {
    "name": "353",
    "position": {
      "x": 2304,
      "y": 1056
    }
  },
  {
    "name": "354",
    "position": {
      "x": 2400,
      "y": 1056
    }
  },
  {
    "name": "355",
    "position": {
      "x": 2496,
      "y": 1056
    }
  },
  {
    "name": "356",
    "position": {
      "x": 2592,
      "y": 1056
    }
  },
  {
    "name": "357",
    "position": {
      "x": 2688,
      "y": 1056
    }
  },
  {
    "name": "358",
    "position": {
      "x": 2784,
      "y": 1056
    }
  },
  {
    "name": "359",
    "position": {
      "x": 2880,
      "y": 1056
    }
  },
  {
    "name": "360",
    "position": {
      "x": 2976,
      "y": 1056
    }
  },
  {
    "name": "361",
    "position": {
      "x": 3072,
      "y": 1056
    }
  },
  {
    "name": "362",
    "position": {
      "x": 0,
      "y": 1152
    }
  },
  {
    "name": "363",
    "position": {
      "x": 96,
      "y": 1152
    }
  },
  {
    "name": "364",
    "position": {
      "x": 192,
      "y": 1152
    }
  },
  {
    "name": "365",
    "position": {
      "x": 288,
      "y": 1152
    }
  },
  {
    "name": "366",
    "position": {
      "x": 384,
      "y": 1152
    }
  },
  {
    "name": "367",
    "position": {
      "x": 480,
      "y": 1152
    }
  },
  {
    "name": "368",
    "position": {
      "x": 576,
      "y": 1152
    }
  },
  {
    "name": "369",
    "position": {
      "x": 672,
      "y": 1152
    }
  },
  {
    "name": "370",
    "position": {
      "x": 768,
      "y": 1152
    }
  },
  {
    "name": "371",
    "position": {
      "x": 864,
      "y": 1152
    }
  },
  {
    "name": "372",
    "position": {
      "x": 960,
      "y": 1152
    }
  },
  {
    "name": "373",
    "position": {
      "x": 1056,
      "y": 1152
    }
  },
  {
    "name": "374",
    "position": {
      "x": 1152,
      "y": 1152
    }
  },
  {
    "name": "375",
    "position": {
      "x": 1248,
      "y": 1152
    }
  },
  {
    "name": "376",
    "position": {
      "x": 1344,
      "y": 1152
    }
  },
  {
    "name": "377",
    "position": {
      "x": 1440,
      "y": 1152
    }
  },
  {
    "name": "378",
    "position": {
      "x": 1536,
      "y": 1152
    }
  },
  {
    "name": "379",
    "position": {
      "x": 1632,
      "y": 1152
    }
  },
  {
    "name": "380",
    "position": {
      "x": 1728,
      "y": 1152
    }
  },
  {
    "name": "381",
    "position": {
      "x": 1824,
      "y": 1152
    }
  },
  {
    "name": "382",
    "position": {
      "x": 1920,
      "y": 1152
    }
  },
  {
    "name": "383",
    "position": {
      "x": 2016,
      "y": 1152
    }
  },
  {
    "name": "384",
    "position": {
      "x": 2112,
      "y": 1152
    }
  },
  {
    "name": "385",
    "position": {
      "x": 2208,
      "y": 1152
    }
  },
  {
    "name": "386-attack",
    "position": {
      "x": 2304,
      "y": 1152
    }
  },
  {
    "name": "386-defense",
    "position": {
      "x": 2400,
      "y": 1152
    }
  },
  {
    "name": "386-normal",
    "position": {
      "x": 2496,
      "y": 1152
    }
  },
  {
    "name": "386-speed",
    "position": {
      "x": 2592,
      "y": 1152
    }
  },
  {
    "name": "386",
    "position": {
      "x": 2688,
      "y": 1152
    }
  },
  {
    "name": "387",
    "position": {
      "x": 2784,
      "y": 1152
    }
  },
  {
    "name": "388",
    "position": {
      "x": 2880,
      "y": 1152
    }
  },
  {
    "name": "389",
    "position": {
      "x": 2976,
      "y": 1152
    }
  },
  {
    "name": "390",
    "position": {
      "x": 3072,
      "y": 1152
    }
  },
  {
    "name": "391",
    "position": {
      "x": 0,
      "y": 1248
    }
  },
  {
    "name": "392",
    "position": {
      "x": 96,
      "y": 1248
    }
  },
  {
    "name": "393",
    "position": {
      "x": 192,
      "y": 1248
    }
  },
  {
    "name": "394",
    "position": {
      "x": 288,
      "y": 1248
    }
  },
  {
    "name": "395",
    "position": {
      "x": 384,
      "y": 1248
    }
  },
  {
    "name": "396",
    "position": {
      "x": 480,
      "y": 1248
    }
  },
  {
    "name": "397",
    "position": {
      "x": 576,
      "y": 1248
    }
  },
  {
    "name": "398",
    "position": {
      "x": 672,
      "y": 1248
    }
  },
  {
    "name": "399",
    "position": {
      "x": 768,
      "y": 1248
    }
  },
  {
    "name": "400",
    "position": {
      "x": 864,
      "y": 1248
    }
  },
  {
    "name": "401",
    "position": {
      "x": 960,
      "y": 1248
    }
  },
  {
    "name": "402",
    "position": {
      "x": 1056,
      "y": 1248
    }
  },
  {
    "name": "403",
    "position": {
      "x": 1152,
      "y": 1248
    }
  },
  {
    "name": "404",
    "position": {
      "x": 1248,
      "y": 1248
    }
  },
  {
    "name": "405",
    "position": {
      "x": 1344,
      "y": 1248
    }
  },
  {
    "name": "406",
    "position": {
      "x": 1440,
      "y": 1248
    }
  },
  {
    "name": "407",
    "position": {
      "x": 1536,
      "y": 1248
    }
  },
  {
    "name": "408",
    "position": {
      "x": 1632,
      "y": 1248
    }
  },
  {
    "name": "409",
    "position": {
      "x": 1728,
      "y": 1248
    }
  },
  {
    "name": "410",
    "position": {
      "x": 1824,
      "y": 1248
    }
  },
  {
    "name": "411",
    "position": {
      "x": 1920,
      "y": 1248
    }
  },
  {
    "name": "412-plant",
    "position": {
      "x": 2016,
      "y": 1248
    }
  },
  {
    "name": "412-sandy",
    "position": {
      "x": 2112,
      "y": 1248
    }
  },
  {
    "name": "412-trash",
    "position": {
      "x": 2208,
      "y": 1248
    }
  },
  {
    "name": "412",
    "position": {
      "x": 2304,
      "y": 1248
    }
  },
  {
    "name": "413-plant",
    "position": {
      "x": 2400,
      "y": 1248
    }
  },
  {
    "name": "413-sandy",
    "position": {
      "x": 2496,
      "y": 1248
    }
  },
  {
    "name": "413-trash",
    "position": {
      "x": 2592,
      "y": 1248
    }
  },
  {
    "name": "413",
    "position": {
      "x": 2688,
      "y": 1248
    }
  },
  {
    "name": "414",
    "position": {
      "x": 2784,
      "y": 1248
    }
  },
  {
    "name": "415",
    "position": {
      "x": 2880,
      "y": 1248
    }
  },
  {
    "name": "416",
    "position": {
      "x": 2976,
      "y": 1248
    }
  },
  {
    "name": "417",
    "position": {
      "x": 3072,
      "y": 1248
    }
  },
  {
    "name": "418",
    "position": {
      "x": 0,
      "y": 1344
    }
  },
  {
    "name": "419",
    "position": {
      "x": 96,
      "y": 1344
    }
  },
  {
    "name": "420",
    "position": {
      "x": 192,
      "y": 1344
    }
  },
  {
    "name": "421-overcast",
    "position": {
      "x": 288,
      "y": 1344
    }
  },
  {
    "name": "421-sunshine",
    "position": {
      "x": 384,
      "y": 1344
    }
  },
  {
    "name": "421",
    "position": {
      "x": 480,
      "y": 1344
    }
  },
  {
    "name": "422-east",
    "position": {
      "x": 576,
      "y": 1344
    }
  },
  {
    "name": "422-west",
    "position": {
      "x": 672,
      "y": 1344
    }
  },
  {
    "name": "422",
    "position": {
      "x": 768,
      "y": 1344
    }
  },
  {
    "name": "423-east",
    "position": {
      "x": 864,
      "y": 1344
    }
  },
  {
    "name": "423-west",
    "position": {
      "x": 960,
      "y": 1344
    }
  },
  {
    "name": "423",
    "position": {
      "x": 1056,
      "y": 1344
    }
  },
  {
    "name": "424",
    "position": {
      "x": 1152,
      "y": 1344
    }
  },
  {
    "name": "425",
    "position": {
      "x": 1248,
      "y": 1344
    }
  },
  {
    "name": "426",
    "position": {
      "x": 1344,
      "y": 1344
    }
  },
  {
    "name": "427",
    "position": {
      "x": 1440,
      "y": 1344
    }
  },
  {
    "name": "428",
    "position": {
      "x": 1536,
      "y": 1344
    }
  },
  {
    "name": "429",
    "position": {
      "x": 1632,
      "y": 1344
    }
  },
  {
    "name": "430",
    "position": {
      "x": 1728,
      "y": 1344
    }
  },
  {
    "name": "431",
    "position": {
      "x": 1824,
      "y": 1344
    }
  },
  {
    "name": "432",
    "position": {
      "x": 1920,
      "y": 1344
    }
  },
  {
    "name": "433",
    "position": {
      "x": 2016,
      "y": 1344
    }
  },
  {
    "name": "434",
    "position": {
      "x": 2112,
      "y": 1344
    }
  },
  {
    "name": "435",
    "position": {
      "x": 2208,
      "y": 1344
    }
  },
  {
    "name": "436",
    "position": {
      "x": 2304,
      "y": 1344
    }
  },
  {
    "name": "437",
    "position": {
      "x": 2400,
      "y": 1344
    }
  },
  {
    "name": "438",
    "position": {
      "x": 2496,
      "y": 1344
    }
  },
  {
    "name": "439",
    "position": {
      "x": 2592,
      "y": 1344
    }
  },
  {
    "name": "440",
    "position": {
      "x": 2688,
      "y": 1344
    }
  },
  {
    "name": "441",
    "position": {
      "x": 2784,
      "y": 1344
    }
  },
  {
    "name": "442",
    "position": {
      "x": 2880,
      "y": 1344
    }
  },
  {
    "name": "443",
    "position": {
      "x": 2976,
      "y": 1344
    }
  },
  {
    "name": "444",
    "position": {
      "x": 3072,
      "y": 1344
    }
  },
  {
    "name": "445",
    "position": {
      "x": 0,
      "y": 1440
    }
  },
  {
    "name": "446",
    "position": {
      "x": 96,
      "y": 1440
    }
  },
  {
    "name": "447",
    "position": {
      "x": 192,
      "y": 1440
    }
  },
  {
    "name": "448",
    "position": {
      "x": 288,
      "y": 1440
    }
  },
  {
    "name": "449",
    "position": {
      "x": 384,
      "y": 1440
    }
  },
  {
    "name": "450",
    "position": {
      "x": 480,
      "y": 1440
    }
  },
  {
    "name": "451",
    "position": {
      "x": 576,
      "y": 1440
    }
  },
  {
    "name": "452",
    "position": {
      "x": 672,
      "y": 1440
    }
  },
  {
    "name": "453",
    "position": {
      "x": 768,
      "y": 1440
    }
  },
  {
    "name": "454",
    "position": {
      "x": 864,
      "y": 1440
    }
  },
  {
    "name": "455",
    "position": {
      "x": 960,
      "y": 1440
    }
  },
  {
    "name": "456",
    "position": {
      "x": 1056,
      "y": 1440
    }
  },
  {
    "name": "457",
    "position": {
      "x": 1152,
      "y": 1440
    }
  },
  {
    "name": "458",
    "position": {
      "x": 1248,
      "y": 1440
    }
  },
  {
    "name": "459",
    "position": {
      "x": 1344,
      "y": 1440
    }
  },
  {
    "name": "460",
    "position": {
      "x": 1440,
      "y": 1440
    }
  },
  {
    "name": "461",
    "position": {
      "x": 1536,
      "y": 1440
    }
  },
  {
    "name": "462",
    "position": {
      "x": 1632,
      "y": 1440
    }
  },
  {
    "name": "463",
    "position": {
      "x": 1728,
      "y": 1440
    }
  },
  {
    "name": "464",
    "position": {
      "x": 1824,
      "y": 1440
    }
  },
  {
    "name": "465",
    "position": {
      "x": 1920,
      "y": 1440
    }
  },
  {
    "name": "466",
    "position": {
      "x": 2016,
      "y": 1440
    }
  },
  {
    "name": "467",
    "position": {
      "x": 2112,
      "y": 1440
    }
  },
  {
    "name": "468",
    "position": {
      "x": 2208,
      "y": 1440
    }
  },
  {
    "name": "469",
    "position": {
      "x": 2304,
      "y": 1440
    }
  },
  {
    "name": "470",
    "position": {
      "x": 2400,
      "y": 1440
    }
  },
  {
    "name": "471",
    "position": {
      "x": 2496,
      "y": 1440
    }
  },
  {
    "name": "472",
    "position": {
      "x": 2592,
      "y": 1440
    }
  },
  {
    "name": "473",
    "position": {
      "x": 2688,
      "y": 1440
    }
  },
  {
    "name": "474",
    "position": {
      "x": 2784,
      "y": 1440
    }
  },
  {
    "name": "475",
    "position": {
      "x": 2880,
      "y": 1440
    }
  },
  {
    "name": "476",
    "position": {
      "x": 2976,
      "y": 1440
    }
  },
  {
    "name": "477",
    "position": {
      "x": 3072,
      "y": 1440
    }
  },
  {
    "name": "478",
    "position": {
      "x": 0,
      "y": 1536
    }
  },
  {
    "name": "479-fan",
    "position": {
      "x": 96,
      "y": 1536
    }
  },
  {
    "name": "479-frost",
    "position": {
      "x": 192,
      "y": 1536
    }
  },
  {
    "name": "479-heat",
    "position": {
      "x": 288,
      "y": 1536
    }
  },
  {
    "name": "479-mow",
    "position": {
      "x": 384,
      "y": 1536
    }
  },
  {
    "name": "479-wash",
    "position": {
      "x": 480,
      "y": 1536
    }
  },
  {
    "name": "479",
    "position": {
      "x": 576,
      "y": 1536
    }
  },
  {
    "name": "480",
    "position": {
      "x": 672,
      "y": 1536
    }
  },
  {
    "name": "481",
    "position": {
      "x": 768,
      "y": 1536
    }
  },
  {
    "name": "482",
    "position": {
      "x": 864,
      "y": 1536
    }
  },
  {
    "name": "483",
    "position": {
      "x": 960,
      "y": 1536
    }
  },
  {
    "name": "484",
    "position": {
      "x": 1056,
      "y": 1536
    }
  },
  {
    "name": "485",
    "position": {
      "x": 1152,
      "y": 1536
    }
  },
  {
    "name": "486",
    "position": {
      "x": 1248,
      "y": 1536
    }
  },
  {
    "name": "487-altered",
    "position": {
      "x": 1344,
      "y": 1536
    }
  },
  {
    "name": "487-origin",
    "position": {
      "x": 1440,
      "y": 1536
    }
  },
  {
    "name": "487",
    "position": {
      "x": 1536,
      "y": 1536
    }
  },
  {
    "name": "488",
    "position": {
      "x": 1632,
      "y": 1536
    }
  },
  {
    "name": "489",
    "position": {
      "x": 1728,
      "y": 1536
    }
  },
  {
    "name": "490",
    "position": {
      "x": 1824,
      "y": 1536
    }
  },
  {
    "name": "491",
    "position": {
      "x": 1920,
      "y": 1536
    }
  },
  {
    "name": "492-land",
    "position": {
      "x": 2016,
      "y": 1536
    }
  },
  {
    "name": "492-sky",
    "position": {
      "x": 2112,
      "y": 1536
    }
  },
  {
    "name": "492",
    "position": {
      "x": 2208,
      "y": 1536
    }
  },
  {
    "name": "493-bug",
    "position": {
      "x": 2304,
      "y": 1536
    }
  },
  {
    "name": "493-dark",
    "position": {
      "x": 2400,
      "y": 1536
    }
  },
  {
    "name": "493-dragon",
    "position": {
      "x": 2496,
      "y": 1536
    }
  },
  {
    "name": "493-electric",
    "position": {
      "x": 2592,
      "y": 1536
    }
  },
  {
    "name": "493-fighting",
    "position": {
      "x": 2688,
      "y": 1536
    }
  },
  {
    "name": "493-fire",
    "position": {
      "x": 2784,
      "y": 1536
    }
  },
  {
    "name": "493-flying",
    "position": {
      "x": 2880,
      "y": 1536
    }
  },
  {
    "name": "493-ghost",
    "position": {
      "x": 2976,
      "y": 1536
    }
  },
  {
    "name": "493-grass",
    "position": {
      "x": 3072,
      "y": 1536
    }
  },
  {
    "name": "493-ground",
    "position": {
      "x": 0,
      "y": 1632
    }
  },
  {
    "name": "493-ice",
    "position": {
      "x": 96,
      "y": 1632
    }
  },
  {
    "name": "493-normal",
    "position": {
      "x": 192,
      "y": 1632
    }
  },
  {
    "name": "493-poison",
    "position": {
      "x": 288,
      "y": 1632
    }
  },
  {
    "name": "493-psychic",
    "position": {
      "x": 384,
      "y": 1632
    }
  },
  {
    "name": "493-rock",
    "position": {
      "x": 480,
      "y": 1632
    }
  },
  {
    "name": "493-steel",
    "position": {
      "x": 576,
      "y": 1632
    }
  },
  {
    "name": "493-unknown",
    "position": {
      "x": 672,
      "y": 1632
    }
  },
  {
    "name": "493-water",
    "position": {
      "x": 768,
      "y": 1632
    }
  },
  {
    "name": "493",
    "position": {
      "x": 864,
      "y": 1632
    }
  },
  {
    "name": "494",
    "position": {
      "x": 960,
      "y": 1632
    }
  },
  {
    "name": "495",
    "position": {
      "x": 1056,
      "y": 1632
    }
  },
  {
    "name": "496",
    "position": {
      "x": 1152,
      "y": 1632
    }
  },
  {
    "name": "497",
    "position": {
      "x": 1248,
      "y": 1632
    }
  },
  {
    "name": "498",
    "position": {
      "x": 1344,
      "y": 1632
    }
  },
  {
    "name": "499",
    "position": {
      "x": 1440,
      "y": 1632
    }
  },
  {
    "name": "500",
    "position": {
      "x": 1536,
      "y": 1632
    }
  },
  {
    "name": "501",
    "position": {
      "x": 1632,
      "y": 1632
    }
  },
  {
    "name": "502",
    "position": {
      "x": 1728,
      "y": 1632
    }
  },
  {
    "name": "503",
    "position": {
      "x": 1824,
      "y": 1632
    }
  },
  {
    "name": "504",
    "position": {
      "x": 1920,
      "y": 1632
    }
  },
  {
    "name": "505",
    "position": {
      "x": 2016,
      "y": 1632
    }
  },
  {
    "name": "506",
    "position": {
      "x": 2112,
      "y": 1632
    }
  },
  {
    "name": "507",
    "position": {
      "x": 2208,
      "y": 1632
    }
  },
  {
    "name": "508",
    "position": {
      "x": 2304,
      "y": 1632
    }
  },
  {
    "name": "509",
    "position": {
      "x": 2400,
      "y": 1632
    }
  },
  {
    "name": "510",
    "position": {
      "x": 2496,
      "y": 1632
    }
  },
  {
    "name": "511",
    "position": {
      "x": 2592,
      "y": 1632
    }
  },
  {
    "name": "512",
    "position": {
      "x": 2688,
      "y": 1632
    }
  },
  {
    "name": "513",
    "position": {
      "x": 2784,
      "y": 1632
    }
  },
  {
    "name": "514",
    "position": {
      "x": 2880,
      "y": 1632
    }
  },
  {
    "name": "515",
    "position": {
      "x": 2976,
      "y": 1632
    }
  },
  {
    "name": "516",
    "position": {
      "x": 3072,
      "y": 1632
    }
  },
  {
    "name": "517",
    "position": {
      "x": 0,
      "y": 1728
    }
  },
  {
    "name": "518",
    "position": {
      "x": 96,
      "y": 1728
    }
  },
  {
    "name": "519",
    "position": {
      "x": 192,
      "y": 1728
    }
  },
  {
    "name": "520",
    "position": {
      "x": 288,
      "y": 1728
    }
  },
  {
    "name": "521",
    "position": {
      "x": 384,
      "y": 1728
    }
  },
  {
    "name": "522",
    "position": {
      "x": 480,
      "y": 1728
    }
  },
  {
    "name": "523",
    "position": {
      "x": 576,
      "y": 1728
    }
  },
  {
    "name": "524",
    "position": {
      "x": 672,
      "y": 1728
    }
  },
  {
    "name": "525",
    "position": {
      "x": 768,
      "y": 1728
    }
  },
  {
    "name": "526",
    "position": {
      "x": 864,
      "y": 1728
    }
  },
  {
    "name": "527",
    "position": {
      "x": 960,
      "y": 1728
    }
  },
  {
    "name": "528",
    "position": {
      "x": 1056,
      "y": 1728
    }
  },
  {
    "name": "529",
    "position": {
      "x": 1152,
      "y": 1728
    }
  },
  {
    "name": "530",
    "position": {
      "x": 1248,
      "y": 1728
    }
  },
  {
    "name": "531",
    "position": {
      "x": 1344,
      "y": 1728
    }
  },
  {
    "name": "532",
    "position": {
      "x": 1440,
      "y": 1728
    }
  },
  {
    "name": "533",
    "position": {
      "x": 1536,
      "y": 1728
    }
  },
  {
    "name": "534",
    "position": {
      "x": 1632,
      "y": 1728
    }
  },
  {
    "name": "535",
    "position": {
      "x": 1728,
      "y": 1728
    }
  },
  {
    "name": "536",
    "position": {
      "x": 1824,
      "y": 1728
    }
  },
  {
    "name": "537",
    "position": {
      "x": 1920,
      "y": 1728
    }
  },
  {
    "name": "538",
    "position": {
      "x": 2016,
      "y": 1728
    }
  },
  {
    "name": "539",
    "position": {
      "x": 2112,
      "y": 1728
    }
  },
  {
    "name": "540",
    "position": {
      "x": 2208,
      "y": 1728
    }
  },
  {
    "name": "541",
    "position": {
      "x": 2304,
      "y": 1728
    }
  },
  {
    "name": "542",
    "position": {
      "x": 2400,
      "y": 1728
    }
  },
  {
    "name": "543",
    "position": {
      "x": 2496,
      "y": 1728
    }
  },
  {
    "name": "544",
    "position": {
      "x": 2592,
      "y": 1728
    }
  },
  {
    "name": "545",
    "position": {
      "x": 2688,
      "y": 1728
    }
  },
  {
    "name": "546",
    "position": {
      "x": 2784,
      "y": 1728
    }
  },
  {
    "name": "547",
    "position": {
      "x": 2880,
      "y": 1728
    }
  },
  {
    "name": "548",
    "position": {
      "x": 2976,
      "y": 1728
    }
  },
  {
    "name": "549",
    "position": {
      "x": 3072,
      "y": 1728
    }
  },
  {
    "name": "550-blue-striped",
    "position": {
      "x": 0,
      "y": 1824
    }
  },
  {
    "name": "550-red-striped",
    "position": {
      "x": 96,
      "y": 1824
    }
  },
  {
    "name": "550",
    "position": {
      "x": 192,
      "y": 1824
    }
  },
  {
    "name": "551",
    "position": {
      "x": 288,
      "y": 1824
    }
  },
  {
    "name": "552",
    "position": {
      "x": 384,
      "y": 1824
    }
  },
  {
    "name": "553",
    "position": {
      "x": 480,
      "y": 1824
    }
  },
  {
    "name": "554",
    "position": {
      "x": 576,
      "y": 1824
    }
  },
  {
    "name": "555-standard",
    "position": {
      "x": 672,
      "y": 1824
    }
  },
  {
    "name": "555-zen",
    "position": {
      "x": 768,
      "y": 1824
    }
  },
  {
    "name": "555",
    "position": {
      "x": 864,
      "y": 1824
    }
  },
  {
    "name": "556",
    "position": {
      "x": 960,
      "y": 1824
    }
  },
  {
    "name": "557",
    "position": {
      "x": 1056,
      "y": 1824
    }
  },
  {
    "name": "558",
    "position": {
      "x": 1152,
      "y": 1824
    }
  },
  {
    "name": "559",
    "position": {
      "x": 1248,
      "y": 1824
    }
  },
  {
    "name": "560",
    "position": {
      "x": 1344,
      "y": 1824
    }
  },
  {
    "name": "561",
    "position": {
      "x": 1440,
      "y": 1824
    }
  },
  {
    "name": "562",
    "position": {
      "x": 1536,
      "y": 1824
    }
  },
  {
    "name": "563",
    "position": {
      "x": 1632,
      "y": 1824
    }
  },
  {
    "name": "564",
    "position": {
      "x": 1728,
      "y": 1824
    }
  },
  {
    "name": "565",
    "position": {
      "x": 1824,
      "y": 1824
    }
  },
  {
    "name": "566",
    "position": {
      "x": 1920,
      "y": 1824
    }
  },
  {
    "name": "567",
    "position": {
      "x": 2016,
      "y": 1824
    }
  },
  {
    "name": "568",
    "position": {
      "x": 2112,
      "y": 1824
    }
  },
  {
    "name": "569",
    "position": {
      "x": 2208,
      "y": 1824
    }
  },
  {
    "name": "570",
    "position": {
      "x": 2304,
      "y": 1824
    }
  },
  {
    "name": "571",
    "position": {
      "x": 2400,
      "y": 1824
    }
  },
  {
    "name": "572",
    "position": {
      "x": 2496,
      "y": 1824
    }
  },
  {
    "name": "573",
    "position": {
      "x": 2592,
      "y": 1824
    }
  },
  {
    "name": "574",
    "position": {
      "x": 2688,
      "y": 1824
    }
  },
  {
    "name": "575",
    "position": {
      "x": 2784,
      "y": 1824
    }
  },
  {
    "name": "576",
    "position": {
      "x": 2880,
      "y": 1824
    }
  },
  {
    "name": "577",
    "position": {
      "x": 2976,
      "y": 1824
    }
  },
  {
    "name": "578",
    "position": {
      "x": 3072,
      "y": 1824
    }
  },
  {
    "name": "579",
    "position": {
      "x": 0,
      "y": 1920
    }
  },
  {
    "name": "580",
    "position": {
      "x": 96,
      "y": 1920
    }
  },
  {
    "name": "581",
    "position": {
      "x": 192,
      "y": 1920
    }
  },
  {
    "name": "582",
    "position": {
      "x": 288,
      "y": 1920
    }
  },
  {
    "name": "583",
    "position": {
      "x": 384,
      "y": 1920
    }
  },
  {
    "name": "584",
    "position": {
      "x": 480,
      "y": 1920
    }
  },
  {
    "name": "585-autumn",
    "position": {
      "x": 576,
      "y": 1920
    }
  },
  {
    "name": "585-spring",
    "position": {
      "x": 672,
      "y": 1920
    }
  },
  {
    "name": "585-summer",
    "position": {
      "x": 768,
      "y": 1920
    }
  },
  {
    "name": "585-winter",
    "position": {
      "x": 864,
      "y": 1920
    }
  },
  {
    "name": "585",
    "position": {
      "x": 960,
      "y": 1920
    }
  },
  {
    "name": "586-autumn",
    "position": {
      "x": 1056,
      "y": 1920
    }
  },
  {
    "name": "586-spring",
    "position": {
      "x": 1152,
      "y": 1920
    }
  },
  {
    "name": "586-summer",
    "position": {
      "x": 1248,
      "y": 1920
    }
  },
  {
    "name": "586-winter",
    "position": {
      "x": 1344,
      "y": 1920
    }
  },
  {
    "name": "586",
    "position": {
      "x": 1440,
      "y": 1920
    }
  },
  {
    "name": "587",
    "position": {
      "x": 1536,
      "y": 1920
    }
  },
  {
    "name": "588",
    "position": {
      "x": 1632,
      "y": 1920
    }
  },
  {
    "name": "589",
    "position": {
      "x": 1728,
      "y": 1920
    }
  },
  {
    "name": "590",
    "position": {
      "x": 1824,
      "y": 1920
    }
  },
  {
    "name": "591",
    "position": {
      "x": 1920,
      "y": 1920
    }
  },
  {
    "name": "592",
    "position": {
      "x": 2016,
      "y": 1920
    }
  },
  {
    "name": "593",
    "position": {
      "x": 2112,
      "y": 1920
    }
  },
  {
    "name": "594",
    "position": {
      "x": 2208,
      "y": 1920
    }
  },
  {
    "name": "595",
    "position": {
      "x": 2304,
      "y": 1920
    }
  },
  {
    "name": "596",
    "position": {
      "x": 2400,
      "y": 1920
    }
  },
  {
    "name": "597",
    "position": {
      "x": 2496,
      "y": 1920
    }
  },
  {
    "name": "598",
    "position": {
      "x": 2592,
      "y": 1920
    }
  },
  {
    "name": "599",
    "position": {
      "x": 2688,
      "y": 1920
    }
  },
  {
    "name": "600",
    "position": {
      "x": 2784,
      "y": 1920
    }
  },
  {
    "name": "601",
    "position": {
      "x": 2880,
      "y": 1920
    }
  },
  {
    "name": "602",
    "position": {
      "x": 2976,
      "y": 1920
    }
  },
  {
    "name": "603",
    "position": {
      "x": 3072,
      "y": 1920
    }
  },
  {
    "name": "604",
    "position": {
      "x": 0,
      "y": 2016
    }
  },
  {
    "name": "605",
    "position": {
      "x": 96,
      "y": 2016
    }
  },
  {
    "name": "606",
    "position": {
      "x": 192,
      "y": 2016
    }
  },
  {
    "name": "607",
    "position": {
      "x": 288,
      "y": 2016
    }
  },
  {
    "name": "608",
    "position": {
      "x": 384,
      "y": 2016
    }
  },
  {
    "name": "609",
    "position": {
      "x": 480,
      "y": 2016
    }
  },
  {
    "name": "610",
    "position": {
      "x": 576,
      "y": 2016
    }
  },
  {
    "name": "611",
    "position": {
      "x": 672,
      "y": 2016
    }
  },
  {
    "name": "612",
    "position": {
      "x": 768,
      "y": 2016
    }
  },
  {
    "name": "613",
    "position": {
      "x": 864,
      "y": 2016
    }
  },
  {
    "name": "614",
    "position": {
      "x": 960,
      "y": 2016
    }
  },
  {
    "name": "615",
    "position": {
      "x": 1056,
      "y": 2016
    }
  },
  {
    "name": "616",
    "position": {
      "x": 1152,
      "y": 2016
    }
  },
  {
    "name": "617",
    "position": {
      "x": 1248,
      "y": 2016
    }
  },
  {
    "name": "618",
    "position": {
      "x": 1344,
      "y": 2016
    }
  },
  {
    "name": "619",
    "position": {
      "x": 1440,
      "y": 2016
    }
  },
  {
    "name": "620",
    "position": {
      "x": 1536,
      "y": 2016
    }
  },
  {
    "name": "621",
    "position": {
      "x": 1632,
      "y": 2016
    }
  },
  {
    "name": "622",
    "position": {
      "x": 1728,
      "y": 2016
    }
  },
  {
    "name": "623",
    "position": {
      "x": 1824,
      "y": 2016
    }
  },
  {
    "name": "624",
    "position": {
      "x": 1920,
      "y": 2016
    }
  },
  {
    "name": "625",
    "position": {
      "x": 2016,
      "y": 2016
    }
  },
  {
    "name": "626",
    "position": {
      "x": 2112,
      "y": 2016
    }
  },
  {
    "name": "627",
    "position": {
      "x": 2208,
      "y": 2016
    }
  },
  {
    "name": "628",
    "position": {
      "x": 2304,
      "y": 2016
    }
  },
  {
    "name": "629",
    "position": {
      "x": 2400,
      "y": 2016
    }
  },
  {
    "name": "630",
    "position": {
      "x": 2496,
      "y": 2016
    }
  },
  {
    "name": "631",
    "position": {
      "x": 2592,
      "y": 2016
    }
  },
  {
    "name": "632",
    "position": {
      "x": 2688,
      "y": 2016
    }
  },
  {
    "name": "633",
    "position": {
      "x": 2784,
      "y": 2016
    }
  },
  {
    "name": "634",
    "position": {
      "x": 2880,
      "y": 2016
    }
  },
  {
    "name": "635",
    "position": {
      "x": 2976,
      "y": 2016
    }
  },
  {
    "name": "636",
    "position": {
      "x": 3072,
      "y": 2016
    }
  },
  {
    "name": "637",
    "position": {
      "x": 0,
      "y": 2112
    }
  },
  {
    "name": "638",
    "position": {
      "x": 96,
      "y": 2112
    }
  },
  {
    "name": "639",
    "position": {
      "x": 192,
      "y": 2112
    }
  },
  {
    "name": "640",
    "position": {
      "x": 288,
      "y": 2112
    }
  },
  {
    "name": "641-incarnate",
    "position": {
      "x": 384,
      "y": 2112
    }
  },
  {
    "name": "641-therian",
    "position": {
      "x": 480,
      "y": 2112
    }
  },
  {
    "name": "641",
    "position": {
      "x": 576,
      "y": 2112
    }
  },
  {
    "name": "642-incarnate",
    "position": {
      "x": 672,
      "y": 2112
    }
  },
  {
    "name": "642-therian",
    "position": {
      "x": 768,
      "y": 2112
    }
  },
  {
    "name": "642",
    "position": {
      "x": 864,
      "y": 2112
    }
  },
  {
    "name": "643",
    "position": {
      "x": 960,
      "y": 2112
    }
  },
  {
    "name": "644",
    "position": {
      "x": 1056,
      "y": 2112
    }
  },
  {
    "name": "645-incarnate",
    "position": {
      "x": 1152,
      "y": 2112
    }
  },
  {
    "name": "645-therian",
    "position": {
      "x": 1248,
      "y": 2112
    }
  },
  {
    "name": "645",
    "position": {
      "x": 1344,
      "y": 2112
    }
  },
  {
    "name": "646-black",
    "position": {
      "x": 1440,
      "y": 2112
    }
  },
  {
    "name": "646-white",
    "position": {
      "x": 1536,
      "y": 2112
    }
  },
  {
    "name": "646",
    "position": {
      "x": 1632,
      "y": 2112
    }
  },
  {
    "name": "647-ordinary",
    "position": {
      "x": 1728,
      "y": 2112
    }
  },
  {
    "name": "647-resolute",
    "position": {
      "x": 1824,
      "y": 2112
    }
  },
  {
    "name": "647",
    "position": {
      "x": 1920,
      "y": 2112
    }
  },
  {
    "name": "648-aria",
    "position": {
      "x": 2016,
      "y": 2112
    }
  },
  {
    "name": "648-pirouette",
    "position": {
      "x": 2112,
      "y": 2112
    }
  },
  {
    "name": "648",
    "position": {
      "x": 2208,
      "y": 2112
    }
  },
  {
    "name": "649-burn",
    "position": {
      "x": 2304,
      "y": 2112
    }
  },
  {
    "name": "649-chill",
    "position": {
      "x": 2400,
      "y": 2112
    }
  },
  {
    "name": "649-douse",
    "position": {
      "x": 2496,
      "y": 2112
    }
  },
  {
    "name": "649-shock",
    "position": {
      "x": 2592,
      "y": 2112
    }
  },
  {
    "name": "649",
    "position": {
      "x": 2688,
      "y": 2112
    }
  },
  {
    "name": "650",
    "position": {
      "x": 2784,
      "y": 2112
    }
  },
  {
    "name": "651",
    "position": {
      "x": 2880,
      "y": 2112
    }
  },
  {
    "name": "652",
    "position": {
      "x": 2976,
      "y": 2112
    }
  },
  {
    "name": "653",
    "position": {
      "x": 3072,
      "y": 2112
    }
  },
  {
    "name": "654",
    "position": {
      "x": 0,
      "y": 2208
    }
  },
  {
    "name": "655",
    "position": {
      "x": 96,
      "y": 2208
    }
  },
  {
    "name": "656",
    "position": {
      "x": 192,
      "y": 2208
    }
  },
  {
    "name": "658",
    "position": {
      "x": 288,
      "y": 2208
    }
  },
  {
    "name": "658_2",
    "position": {
      "x": 384,
      "y": 2208
    }
  },
  {
    "name": "659",
    "position": {
      "x": 480,
      "y": 2208
    }
  },
  {
    "name": "663",
    "position": {
      "x": 576,
      "y": 2208
    }
  },
  {
    "name": "665",
    "position": {
      "x": 672,
      "y": 2208
    }
  },
  {
    "name": "667",
    "position": {
      "x": 768,
      "y": 2208
    }
  },
  {
    "name": "672",
    "position": {
      "x": 864,
      "y": 2208
    }
  },
  {
    "name": "674",
    "position": {
      "x": 960,
      "y": 2208
    }
  },
  {
    "name": "675",
    "position": {
      "x": 1056,
      "y": 2208
    }
  },
  {
    "name": "677",
    "position": {
      "x": 1152,
      "y": 2208
    }
  },
  {
    "name": "682",
    "position": {
      "x": 1248,
      "y": 2208
    }
  },
  {
    "name": "683",
    "position": {
      "x": 1344,
      "y": 2208
    }
  },
  {
    "name": "684",
    "position": {
      "x": 1440,
      "y": 2208
    }
  },
  {
    "name": "685",
    "position": {
      "x": 1536,
      "y": 2208
    }
  },
  {
    "name": "686",
    "position": {
      "x": 1632,
      "y": 2208
    }
  },
  {
    "name": "688",
    "position": {
      "x": 1728,
      "y": 2208
    }
  },
  {
    "name": "690",
    "position": {
      "x": 1824,
      "y": 2208
    }
  },
  {
    "name": "692",
    "position": {
      "x": 1920,
      "y": 2208
    }
  },
  {
    "name": "694",
    "position": {
      "x": 2016,
      "y": 2208
    }
  },
  {
    "name": "697",
    "position": {
      "x": 2112,
      "y": 2208
    }
  },
  {
    "name": "701",
    "position": {
      "x": 2208,
      "y": 2208
    }
  },
  {
    "name": "702",
    "position": {
      "x": 2304,
      "y": 2208
    }
  },
  {
    "name": "703",
    "position": {
      "x": 2400,
      "y": 2208
    }
  },
  {
    "name": "704",
    "position": {
      "x": 2496,
      "y": 2208
    }
  },
  {
    "name": "707",
    "position": {
      "x": 2592,
      "y": 2208
    }
  },
  {
    "name": "708",
    "position": {
      "x": 2688,
      "y": 2208
    }
  },
  {
    "name": "710",
    "position": {
      "x": 2784,
      "y": 2208
    }
  },
  {
    "name": "712",
    "position": {
      "x": 2880,
      "y": 2208
    }
  },
  {
    "name": "718_2",
    "position": {
      "x": 2976,
      "y": 2208
    }
  },
  {
    "name": "718_3",
    "position": {
      "x": 3072,
      "y": 2208
    }
  },
  {
    "name": "720",
    "position": {
      "x": 0,
      "y": 2304
    }
  },
  {
    "name": "722",
    "position": {
      "x": 96,
      "y": 2304
    }
  },
  {
    "name": "723",
    "position": {
      "x": 192,
      "y": 2304
    }
  },
  {
    "name": "724",
    "position": {
      "x": 288,
      "y": 2304
    }
  },
  {
    "name": "725",
    "position": {
      "x": 384,
      "y": 2304
    }
  },
  {
    "name": "726",
    "position": {
      "x": 480,
      "y": 2304
    }
  },
  {
    "name": "727",
    "position": {
      "x": 576,
      "y": 2304
    }
  },
  {
    "name": "728",
    "position": {
      "x": 672,
      "y": 2304
    }
  },
  {
    "name": "729",
    "position": {
      "x": 768,
      "y": 2304
    }
  },
  {
    "name": "730",
    "position": {
      "x": 864,
      "y": 2304
    }
  },
  {
    "name": "731",
    "position": {
      "x": 960,
      "y": 2304
    }
  },
  {
    "name": "732",
    "position": {
      "x": 1056,
      "y": 2304
    }
  },
  {
    "name": "733",
    "position": {
      "x": 1152,
      "y": 2304
    }
  },
  {
    "name": "734",
    "position": {
      "x": 1248,
      "y": 2304
    }
  },
  {
    "name": "735",
    "position": {
      "x": 1344,
      "y": 2304
    }
  },
  {
    "name": "736",
    "position": {
      "x": 1440,
      "y": 2304
    }
  },
  {
    "name": "737",
    "position": {
      "x": 1536,
      "y": 2304
    }
  },
  {
    "name": "738",
    "position": {
      "x": 1632,
      "y": 2304
    }
  },
  {
    "name": "739",
    "position": {
      "x": 1728,
      "y": 2304
    }
  },
  {
    "name": "740",
    "position": {
      "x": 1824,
      "y": 2304
    }
  },
  {
    "name": "741",
    "position": {
      "x": 1920,
      "y": 2304
    }
  },
  {
    "name": "742",
    "position": {
      "x": 2016,
      "y": 2304
    }
  },
  {
    "name": "743",
    "position": {
      "x": 2112,
      "y": 2304
    }
  },
  {
    "name": "744",
    "position": {
      "x": 2208,
      "y": 2304
    }
  },
  {
    "name": "745",
    "position": {
      "x": 2304,
      "y": 2304
    }
  },
  {
    "name": "746",
    "position": {
      "x": 2400,
      "y": 2304
    }
  },
  {
    "name": "747",
    "position": {
      "x": 2496,
      "y": 2304
    }
  },
  {
    "name": "748",
    "position": {
      "x": 2592,
      "y": 2304
    }
  },
  {
    "name": "749",
    "position": {
      "x": 2688,
      "y": 2304
    }
  },
  {
    "name": "750",
    "position": {
      "x": 2784,
      "y": 2304
    }
  },
  {
    "name": "751",
    "position": {
      "x": 2880,
      "y": 2304
    }
  },
  {
    "name": "752",
    "position": {
      "x": 2976,
      "y": 2304
    }
  },
  {
    "name": "753",
    "position": {
      "x": 3072,
      "y": 2304
    }
  },
  {
    "name": "754",
    "position": {
      "x": 0,
      "y": 2400
    }
  },
  {
    "name": "755",
    "position": {
      "x": 96,
      "y": 2400
    }
  },
  {
    "name": "756",
    "position": {
      "x": 192,
      "y": 2400
    }
  },
  {
    "name": "757",
    "position": {
      "x": 288,
      "y": 2400
    }
  },
  {
    "name": "758",
    "position": {
      "x": 384,
      "y": 2400
    }
  },
  {
    "name": "759",
    "position": {
      "x": 480,
      "y": 2400
    }
  },
  {
    "name": "760",
    "position": {
      "x": 576,
      "y": 2400
    }
  },
  {
    "name": "761",
    "position": {
      "x": 672,
      "y": 2400
    }
  },
  {
    "name": "762",
    "position": {
      "x": 768,
      "y": 2400
    }
  },
  {
    "name": "763",
    "position": {
      "x": 864,
      "y": 2400
    }
  },
  {
    "name": "764",
    "position": {
      "x": 960,
      "y": 2400
    }
  },
  {
    "name": "765",
    "position": {
      "x": 1056,
      "y": 2400
    }
  },
  {
    "name": "766",
    "position": {
      "x": 1152,
      "y": 2400
    }
  },
  {
    "name": "767",
    "position": {
      "x": 1248,
      "y": 2400
    }
  },
  {
    "name": "768",
    "position": {
      "x": 1344,
      "y": 2400
    }
  },
  {
    "name": "769",
    "position": {
      "x": 1440,
      "y": 2400
    }
  },
  {
    "name": "770",
    "position": {
      "x": 1536,
      "y": 2400
    }
  },
  {
    "name": "771",
    "position": {
      "x": 1632,
      "y": 2400
    }
  },
  {
    "name": "772",
    "position": {
      "x": 1728,
      "y": 2400
    }
  },
  {
    "name": "773",
    "position": {
      "x": 1824,
      "y": 2400
    }
  },
  {
    "name": "774",
    "position": {
      "x": 1920,
      "y": 2400
    }
  },
  {
    "name": "775",
    "position": {
      "x": 2016,
      "y": 2400
    }
  },
  {
    "name": "776",
    "position": {
      "x": 2112,
      "y": 2400
    }
  },
  {
    "name": "777",
    "position": {
      "x": 2208,
      "y": 2400
    }
  },
  {
    "name": "778",
    "position": {
      "x": 2304,
      "y": 2400
    }
  },
  {
    "name": "779",
    "position": {
      "x": 2400,
      "y": 2400
    }
  },
  {
    "name": "780",
    "position": {
      "x": 2496,
      "y": 2400
    }
  },
  {
    "name": "781",
    "position": {
      "x": 2592,
      "y": 2400
    }
  },
  {
    "name": "782",
    "position": {
      "x": 2688,
      "y": 2400
    }
  },
  {
    "name": "783",
    "position": {
      "x": 2784,
      "y": 2400
    }
  },
  {
    "name": "784",
    "position": {
      "x": 2880,
      "y": 2400
    }
  },
  {
    "name": "785",
    "position": {
      "x": 2976,
      "y": 2400
    }
  },
  {
    "name": "786",
    "position": {
      "x": 3072,
      "y": 2400
    }
  },
  {
    "name": "787",
    "position": {
      "x": 0,
      "y": 2496
    }
  },
  {
    "name": "788",
    "position": {
      "x": 96,
      "y": 2496
    }
  },
  {
    "name": "789",
    "position": {
      "x": 192,
      "y": 2496
    }
  },
  {
    "name": "790",
    "position": {
      "x": 288,
      "y": 2496
    }
  },
  {
    "name": "791",
    "position": {
      "x": 384,
      "y": 2496
    }
  },
  {
    "name": "792",
    "position": {
      "x": 480,
      "y": 2496
    }
  },
  {
    "name": "793",
    "position": {
      "x": 576,
      "y": 2496
    }
  },
  {
    "name": "794",
    "position": {
      "x": 672,
      "y": 2496
    }
  },
  {
    "name": "795",
    "position": {
      "x": 768,
      "y": 2496
    }
  },
  {
    "name": "796",
    "position": {
      "x": 864,
      "y": 2496
    }
  },
  {
    "name": "797",
    "position": {
      "x": 960,
      "y": 2496
    }
  },
  {
    "name": "798",
    "position": {
      "x": 1056,
      "y": 2496
    }
  },
  {
    "name": "799",
    "position": {
      "x": 1152,
      "y": 2496
    }
  },
  {
    "name": "800",
    "position": {
      "x": 1248,
      "y": 2496
    }
  },
  {
    "name": "801",
    "position": {
      "x": 1344,
      "y": 2496
    }
  },
  {
    "name": "802",
    "position": {
      "x": 1440,
      "y": 2496
    }
  },
  {
    "name": "803",
    "position": {
      "x": 1536,
      "y": 2496
    }
  },
  {
    "name": "804",
    "position": {
      "x": 1632,
      "y": 2496
    }
  },
  {
    "name": "805",
    "position": {
      "x": 1728,
      "y": 2496
    }
  },
  {
    "name": "806",
    "position": {
      "x": 1824,
      "y": 2496
    }
  },
  {
    "name": "807",
    "position": {
      "x": 1920,
      "y": 2496
    }
  },
  {
    "name": "808",
    "position": {
      "x": 2016,
      "y": 2496
    }
  },
  {
    "name": "809",
    "position": {
      "x": 2112,
      "y": 2496
    }
  },
  {
    "name": "810",
    "position": {
      "x": 2208,
      "y": 2496
    }
  },
  {
    "name": "811",
    "position": {
      "x": 2304,
      "y": 2496
    }
  },
  {
    "name": "812",
    "position": {
      "x": 2400,
      "y": 2496
    }
  },
  {
    "name": "813",
    "position": {
      "x": 2496,
      "y": 2496
    }
  },
  {
    "name": "814",
    "position": {
      "x": 2592,
      "y": 2496
    }
  },
  {
    "name": "815",
    "position": {
      "x": 2688,
      "y": 2496
    }
  },
  {
    "name": "816",
    "position": {
      "x": 2784,
      "y": 2496
    }
  },
  {
    "name": "817",
    "position": {
      "x": 2880,
      "y": 2496
    }
  },
  {
    "name": "818",
    "position": {
      "x": 2976,
      "y": 2496
    }
  },
  {
    "name": "819",
    "position": {
      "x": 3072,
      "y": 2496
    }
  },
  {
    "name": "820",
    "position": {
      "x": 0,
      "y": 2592
    }
  },
  {
    "name": "821",
    "position": {
      "x": 96,
      "y": 2592
    }
  },
  {
    "name": "822",
    "position": {
      "x": 192,
      "y": 2592
    }
  },
  {
    "name": "823",
    "position": {
      "x": 288,
      "y": 2592
    }
  },
  {
    "name": "824",
    "position": {
      "x": 384,
      "y": 2592
    }
  },
  {
    "name": "825",
    "position": {
      "x": 480,
      "y": 2592
    }
  },
  {
    "name": "826",
    "position": {
      "x": 576,
      "y": 2592
    }
  },
  {
    "name": "827",
    "position": {
      "x": 672,
      "y": 2592
    }
  },
  {
    "name": "828",
    "position": {
      "x": 768,
      "y": 2592
    }
  },
  {
    "name": "829",
    "position": {
      "x": 864,
      "y": 2592
    }
  },
  {
    "name": "830",
    "position": {
      "x": 960,
      "y": 2592
    }
  },
  {
    "name": "831",
    "position": {
      "x": 1056,
      "y": 2592
    }
  },
  {
    "name": "832",
    "position": {
      "x": 1152,
      "y": 2592
    }
  },
  {
    "name": "833",
    "position": {
      "x": 1248,
      "y": 2592
    }
  },
  {
    "name": "834",
    "position": {
      "x": 1344,
      "y": 2592
    }
  },
  {
    "name": "835",
    "position": {
      "x": 1440,
      "y": 2592
    }
  },
  {
    "name": "836",
    "position": {
      "x": 1536,
      "y": 2592
    }
  },
  {
    "name": "837",
    "position": {
      "x": 1632,
      "y": 2592
    }
  },
  {
    "name": "838",
    "position": {
      "x": 1728,
      "y": 2592
    }
  },
  {
    "name": "839",
    "position": {
      "x": 1824,
      "y": 2592
    }
  },
  {
    "name": "840",
    "position": {
      "x": 1920,
      "y": 2592
    }
  },
  {
    "name": "841",
    "position": {
      "x": 2016,
      "y": 2592
    }
  },
  {
    "name": "842",
    "position": {
      "x": 2112,
      "y": 2592
    }
  },
  {
    "name": "843",
    "position": {
      "x": 2208,
      "y": 2592
    }
  },
  {
    "name": "844",
    "position": {
      "x": 2304,
      "y": 2592
    }
  },
  {
    "name": "845",
    "position": {
      "x": 2400,
      "y": 2592
    }
  },
  {
    "name": "846",
    "position": {
      "x": 2496,
      "y": 2592
    }
  },
  {
    "name": "847",
    "position": {
      "x": 2592,
      "y": 2592
    }
  },
  {
    "name": "848",
    "position": {
      "x": 2688,
      "y": 2592
    }
  },
  {
    "name": "849",
    "position": {
      "x": 2784,
      "y": 2592
    }
  },
  {
    "name": "850",
    "position": {
      "x": 2880,
      "y": 2592
    }
  },
  {
    "name": "851",
    "position": {
      "x": 2976,
      "y": 2592
    }
  },
  {
    "name": "852",
    "position": {
      "x": 3072,
      "y": 2592
    }
  },
  {
    "name": "853",
    "position": {
      "x": 0,
      "y": 2688
    }
  },
  {
    "name": "854",
    "position": {
      "x": 96,
      "y": 2688
    }
  },
  {
    "name": "855",
    "position": {
      "x": 192,
      "y": 2688
    }
  },
  {
    "name": "856",
    "position": {
      "x": 288,
      "y": 2688
    }
  },
  {
    "name": "857",
    "position": {
      "x": 384,
      "y": 2688
    }
  },
  {
    "name": "858",
    "position": {
      "x": 480,
      "y": 2688
    }
  },
  {
    "name": "859",
    "position": {
      "x": 576,
      "y": 2688
    }
  },
  {
    "name": "860",
    "position": {
      "x": 672,
      "y": 2688
    }
  },
  {
    "name": "861",
    "position": {
      "x": 768,
      "y": 2688
    }
  },
  {
    "name": "862",
    "position": {
      "x": 864,
      "y": 2688
    }
  },
  {
    "name": "863",
    "position": {
      "x": 960,
      "y": 2688
    }
  },
  {
    "name": "864",
    "position": {
      "x": 1056,
      "y": 2688
    }
  },
  {
    "name": "865",
    "position": {
      "x": 1152,
      "y": 2688
    }
  },
  {
    "name": "866",
    "position": {
      "x": 1248,
      "y": 2688
    }
  },
  {
    "name": "867",
    "position": {
      "x": 1344,
      "y": 2688
    }
  },
  {
    "name": "868",
    "position": {
      "x": 1440,
      "y": 2688
    }
  },
  {
    "name": "869",
    "position": {
      "x": 1536,
      "y": 2688
    }
  },
  {
    "name": "870",
    "position": {
      "x": 1632,
      "y": 2688
    }
  },
  {
    "name": "871",
    "position": {
      "x": 1728,
      "y": 2688
    }
  },
  {
    "name": "872",
    "position": {
      "x": 1824,
      "y": 2688
    }
  },
  {
    "name": "873",
    "position": {
      "x": 1920,
      "y": 2688
    }
  },
  {
    "name": "874",
    "position": {
      "x": 2016,
      "y": 2688
    }
  },
  {
    "name": "875",
    "position": {
      "x": 2112,
      "y": 2688
    }
  },
  {
    "name": "876",
    "position": {
      "x": 2208,
      "y": 2688
    }
  },
  {
    "name": "877",
    "position": {
      "x": 2304,
      "y": 2688
    }
  },
  {
    "name": "878",
    "position": {
      "x": 2400,
      "y": 2688
    }
  },
  {
    "name": "879",
    "position": {
      "x": 2496,
      "y": 2688
    }
  },
  {
    "name": "880",
    "position": {
      "x": 2592,
      "y": 2688
    }
  },
  {
    "name": "881",
    "position": {
      "x": 2688,
      "y": 2688
    }
  },
  {
    "name": "882",
    "position": {
      "x": 2784,
      "y": 2688
    }
  },
  {
    "name": "883",
    "position": {
      "x": 2880,
      "y": 2688
    }
  },
  {
    "name": "884",
    "position": {
      "x": 2976,
      "y": 2688
    }
  },
  {
    "name": "885",
    "position": {
      "x": 3072,
      "y": 2688
    }
  },
  {
    "name": "886",
    "position": {
      "x": 0,
      "y": 2784
    }
  },
  {
    "name": "887",
    "position": {
      "x": 96,
      "y": 2784
    }
  },
  {
    "name": "888",
    "position": {
      "x": 192,
      "y": 2784
    }
  },
  {
    "name": "889",
    "position": {
      "x": 288,
      "y": 2784
    }
  },
  {
    "name": "890",
    "position": {
      "x": 384,
      "y": 2784
    }
  },
  {
    "name": "891",
    "position": {
      "x": 480,
      "y": 2784
    }
  },
  {
    "name": "892",
    "position": {
      "x": 576,
      "y": 2784
    }
  },
  {
    "name": "893",
    "position": {
      "x": 672,
      "y": 2784
    }
  },
  {
    "name": "894",
    "position": {
      "x": 768,
      "y": 2784
    }
  },
  {
    "name": "895",
    "position": {
      "x": 864,
      "y": 2784
    }
  },
  {
    "name": "896",
    "position": {
      "x": 960,
      "y": 2784
    }
  },
  {
    "name": "897",
    "position": {
      "x": 1056,
      "y": 2784
    }
  },
  {
    "name": "898",
    "position": {
      "x": 1152,
      "y": 2784
    }
  },
  {
    "name": "10033",
    "position": {
      "x": 1248,
      "y": 2784
    }
  },
  {
    "name": "10037",
    "position": {
      "x": 1344,
      "y": 2784
    }
  },
  {
    "name": "10039",
    "position": {
      "x": 1440,
      "y": 2784
    }
  },
  {
    "name": "10045",
    "position": {
      "x": 1536,
      "y": 2784
    }
  },
  {
    "name": "10047",
    "position": {
      "x": 1632,
      "y": 2784
    }
  },
  {
    "name": "10056",
    "position": {
      "x": 1728,
      "y": 2784
    }
  },
  {
    "name": "10061",
    "position": {
      "x": 1824,
      "y": 2784
    }
  },
  {
    "name": "10067",
    "position": {
      "x": 1920,
      "y": 2784
    }
  },
  {
    "name": "10070",
    "position": {
      "x": 2016,
      "y": 2784
    }
  },
  {
    "name": "10074",
    "position": {
      "x": 2112,
      "y": 2784
    }
  },
  {
    "name": "10079",
    "position": {
      "x": 2208,
      "y": 2784
    }
  },
  {
    "name": "10080",
    "position": {
      "x": 2304,
      "y": 2784
    }
  },
  {
    "name": "10081",
    "position": {
      "x": 2400,
      "y": 2784
    }
  },
  {
    "name": "10082",
    "position": {
      "x": 2496,
      "y": 2784
    }
  },
  {
    "name": "10083",
    "position": {
      "x": 2592,
      "y": 2784
    }
  },
  {
    "name": "10084",
    "position": {
      "x": 2688,
      "y": 2784
    }
  },
  {
    "name": "10085",
    "position": {
      "x": 2784,
      "y": 2784
    }
  },
  {
    "name": "10089",
    "position": {
      "x": 2880,
      "y": 2784
    }
  },
  {
    "name": "10091",
    "position": {
      "x": 2976,
      "y": 2784
    }
  },
  {
    "name": "10092",
    "position": {
      "x": 3072,
      "y": 2784
    }
  },
  {
    "name": "10100",
    "position": {
      "x": 0,
      "y": 2880
    }
  },
  {
    "name": "10101",
    "position": {
      "x": 96,
      "y": 2880
    }
  },
  {
    "name": "10102",
    "position": {
      "x": 192,
      "y": 2880
    }
  },
  {
    "name": "10103",
    "position": {
      "x": 288,
      "y": 2880
    }
  },
  {
    "name": "10104",
    "position": {
      "x": 384,
      "y": 2880
    }
  },
  {
    "name": "10105",
    "position": {
      "x": 480,
      "y": 2880
    }
  },
  {
    "name": "10106",
    "position": {
      "x": 576,
      "y": 2880
    }
  },
  {
    "name": "10107",
    "position": {
      "x": 672,
      "y": 2880
    }
  },
  {
    "name": "10108",
    "position": {
      "x": 768,
      "y": 2880
    }
  },
  {
    "name": "10109",
    "position": {
      "x": 864,
      "y": 2880
    }
  },
  {
    "name": "10110",
    "position": {
      "x": 960,
      "y": 2880
    }
  },
  {
    "name": "10111",
    "position": {
      "x": 1056,
      "y": 2880
    }
  },
  {
    "name": "10112",
    "position": {
      "x": 1152,
      "y": 2880
    }
  },
  {
    "name": "10113",
    "position": {
      "x": 1248,
      "y": 2880
    }
  },
  {
    "name": "10114",
    "position": {
      "x": 1344,
      "y": 2880
    }
  },
  {
    "name": "10115",
    "position": {
      "x": 1440,
      "y": 2880
    }
  },
  {
    "name": "10116",
    "position": {
      "x": 1536,
      "y": 2880
    }
  },
  {
    "name": "10118",
    "position": {
      "x": 1632,
      "y": 2880
    }
  },
  {
    "name": "10119",
    "position": {
      "x": 1728,
      "y": 2880
    }
  },
  {
    "name": "10120",
    "position": {
      "x": 1824,
      "y": 2880
    }
  },
  {
    "name": "10123",
    "position": {
      "x": 1920,
      "y": 2880
    }
  },
  {
    "name": "10124",
    "position": {
      "x": 2016,
      "y": 2880
    }
  },
  {
    "name": "10125",
    "position": {
      "x": 2112,
      "y": 2880
    }
  },
  {
    "name": "10126",
    "position": {
      "x": 2208,
      "y": 2880
    }
  },
  {
    "name": "10127",
    "position": {
      "x": 2304,
      "y": 2880
    }
  },
  {
    "name": "10136",
    "position": {
      "x": 2400,
      "y": 2880
    }
  },
  {
    "name": "10137",
    "position": {
      "x": 2496,
      "y": 2880
    }
  },
  {
    "name": "10138",
    "position": {
      "x": 2592,
      "y": 2880
    }
  },
  {
    "name": "10139",
    "position": {
      "x": 2688,
      "y": 2880
    }
  },
  {
    "name": "10140",
    "position": {
      "x": 2784,
      "y": 2880
    }
  },
  {
    "name": "10141",
    "position": {
      "x": 2880,
      "y": 2880
    }
  },
  {
    "name": "10142",
    "position": {
      "x": 2976,
      "y": 2880
    }
  },
  {
    "name": "10143",
    "position": {
      "x": 3072,
      "y": 2880
    }
  },
  {
    "name": "10147",
    "position": {
      "x": 0,
      "y": 2976
    }
  },
  {
    "name": "10152",
    "position": {
      "x": 96,
      "y": 2976
    }
  },
  {
    "name": "10155",
    "position": {
      "x": 192,
      "y": 2976
    }
  },
  {
    "name": "10156",
    "position": {
      "x": 288,
      "y": 2976
    }
  },
  {
    "name": "10157",
    "position": {
      "x": 384,
      "y": 2976
    }
  },
  {
    "name": "10161",
    "position": {
      "x": 480,
      "y": 2976
    }
  },
  {
    "name": "10162",
    "position": {
      "x": 576,
      "y": 2976
    }
  },
  {
    "name": "10163",
    "position": {
      "x": 672,
      "y": 2976
    }
  },
  {
    "name": "10164",
    "position": {
      "x": 768,
      "y": 2976
    }
  },
  {
    "name": "10165",
    "position": {
      "x": 864,
      "y": 2976
    }
  },
  {
    "name": "10166",
    "position": {
      "x": 960,
      "y": 2976
    }
  },
  {
    "name": "10167",
    "position": {
      "x": 1056,
      "y": 2976
    }
  },
  {
    "name": "10168",
    "position": {
      "x": 1152,
      "y": 2976
    }
  },
  {
    "name": "10169",
    "position": {
      "x": 1248,
      "y": 2976
    }
  },
  {
    "name": "10170",
    "position": {
      "x": 1344,
      "y": 2976
    }
  },
  {
    "name": "10171",
    "position": {
      "x": 1440,
      "y": 2976
    }
  },
  {
    "name": "10172",
    "position": {
      "x": 1536,
      "y": 2976
    }
  },
  {
    "name": "10173",
    "position": {
      "x": 1632,
      "y": 2976
    }
  },
  {
    "name": "10174",
    "position": {
      "x": 1728,
      "y": 2976
    }
  },
  {
    "name": "10175",
    "position": {
      "x": 1824,
      "y": 2976
    }
  },
  {
    "name": "10176",
    "position": {
      "x": 1920,
      "y": 2976
    }
  },
  {
    "name": "10177",
    "position": {
      "x": 2016,
      "y": 2976
    }
  },
  {
    "name": "10178",
    "position": {
      "x": 2112,
      "y": 2976
    }
  },
  {
    "name": "10179",
    "position": {
      "x": 2208,
      "y": 2976
    }
  },
  {
    "name": "10180",
    "position": {
      "x": 2304,
      "y": 2976
    }
  },
  {
    "name": "10184",
    "position": {
      "x": 2400,
      "y": 2976
    }
  },
  {
    "name": "10185",
    "position": {
      "x": 2496,
      "y": 2976
    }
  },
  {
    "name": "10188",
    "position": {
      "x": 2592,
      "y": 2976
    }
  },
  {
    "name": "10189",
    "position": {
      "x": 2688,
      "y": 2976
    }
  },
  {
    "name": "10191",
    "position": {
      "x": 2784,
      "y": 2976
    }
  },
  {
    "name": "10193",
    "position": {
      "x": 2880,
      "y": 2976
    }
  },
  {
    "name": "10194",
    "position": {
      "x": 2976,
      "y": 2976
    }
  },
  {
    "name": "10195",
    "position": {
      "x": 3072,
      "y": 2976
    }
  },
  {
    "name": "10196",
    "position": {
      "x": 0,
      "y": 3072
    }
  },
  {
    "name": "10197",
    "position": {
      "x": 96,
      "y": 3072
    }
  },
  {
    "name": "10198",
    "position": {
      "x": 192,
      "y": 3072
    }
  },
  {
    "name": "10199",
    "position": {
      "x": 288,
      "y": 3072
    }
  },
  {
    "name": "10200",
    "position": {
      "x": 384,
      "y": 3072
    }
  },
  {
    "name": "10201",
    "position": {
      "x": 480,
      "y": 3072
    }
  },
  {
    "name": "10202",
    "position": {
      "x": 576,
      "y": 3072
    }
  },
  {
    "name": "10203",
    "position": {
      "x": 672,
      "y": 3072
    }
  },
  {
    "name": "10204",
    "position": {
      "x": 768,
      "y": 3072
    }
  },
  {
    "name": "10205",
    "position": {
      "x": 864,
      "y": 3072
    }
  },
  {
    "name": "10206",
    "position": {
      "x": 960,
      "y": 3072
    }
  },
  {
    "name": "10207",
    "position": {
      "x": 1056,
      "y": 3072
    }
  },
  {
    "name": "10208",
    "position": {
      "x": 1152,
      "y": 3072
    }
  },
  {
    "name": "10209",
    "position": {
      "x": 1248,
      "y": 3072
    }
  },
  {
    "name": "10210",
    "position": {
      "x": 1344,
      "y": 3072
    }
  },
  {
    "name": "10211",
    "position": {
      "x": 1440,
      "y": 3072
    }
  },
  {
    "name": "10212",
    "position": {
      "x": 1536,
      "y": 3072
    }
  },
  {
    "name": "10213",
    "position": {
      "x": 1632,
      "y": 3072
    }
  },
  {
    "name": "10214",
    "position": {
      "x": 1728,
      "y": 3072
    }
  },
  {
    "name": "10215",
    "position": {
      "x": 1824,
      "y": 3072
    }
  },
  {
    "name": "10218",
    "position": {
      "x": 1920,
      "y": 3072
    }
  },
  {
    "name": "10220",
    "position": {
      "x": 2016,
      "y": 3072
    }
  },
  {
    "name": "10221",
    "position": {
      "x": 2112,
      "y": 3072
    }
  },
  {
    "name": "10222",
    "position": {
      "x": 2208,
      "y": 3072
    }
  },
  {
    "name": "10223",
    "position": {
      "x": 2304,
      "y": 3072
    }
  },
  {
    "name": "10224",
    "position": {
      "x": 2400,
      "y": 3072
    }
  },
  {
    "name": "10225",
    "position": {
      "x": 2496,
      "y": 3072
    }
  }
]